{
  "document_path": "raw/ORD_files/Contribute/Penedo/application/EPFL_Penedo_4th_call.pdf",
  "status": "success",
  "data": {
    "project_category": "Contribute Projects",
    "main_applicant_institution": "EPFL",
    "main_applicant_function": "Scientist",
    "main_applicant_first_name": "Marcos",
    "main_applicant_surname": "Penedo Garcia",
    "main_applicant_laboratory_name": "EPFL STI IBI-STI LBNI (Laboratory for Bio- and Nano-Instrumentation)",
    "main_applicant_postcode": 1015,
    "main_applicant_city": "Lausanne",
    "all_applicants": [
      {
        "eth_domain_institution": "EPFL",
        "function_title": "Scientist",
        "first_name": "Marcos",
        "surname": "Penedo Garcia",
        "postcode": 1015
      }
    ],
    "project_title": "HDF5-USID scheme implementation in the Open-Source SPM project for Pycroscopy ecosystems",
    "project_acronym": "PySPM",
    "project_abstract": "Open-source data schemes are becoming increasingly important for scientific data storage. They enable sharing of software, data, and knowledge at early phases in the scientific process, as well as proper long-term preservation storage. In this project, we aim to implement the HDF5 and USID open standards on an already well-established ORD worldwide project at EPFL: the Open-Source SPM controller. Its current file scheme presents several weaknesses that we intend to overcome with those modern standards. Furthermore, the implementation of this scheme will enable the access to a lively open software ecosystem called Pycroscopy, where the Open-Source SPM project will take advantage of all the functionalities and tools already existing on that ecosystem based on the HDF5 and USID open standards.",
    "keywords": [
      "HDF5",
      "USID",
      "Pycroscopy",
      "SPM",
      "Open-Hardware"
    ],
    "start_date": "1 Feb 2024",
    "project_duration_months": 6,
    "total_budget_requested": 30000.0,
    "work_packages": [
      {
        "wp_identifier": "WP1",
        "wp_title": "USID scheme design for the techniques involved on the Open-Source controller"
      },
      {
        "wp_identifier": "WP2",
        "wp_title": "New FPGA-PC communication protocol for efficient high-speed data transfer"
      },
      {
        "wp_identifier": "WP3",
        "wp_title": "Implement the designed USID scheme into a HDF5 file format"
      },
      {
        "wp_identifier": "WP4",
        "wp_title": "HDF5-USID/Gwyddion conversion tools"
      }
    ]
  },
  "metadata": {
    "schema_name": "ORDMetadata",
    "extraction_mode": "PREMIUM",
    "attempts": 1
  },
  "extraction_metadata": {
    "field_metadata": {
      "project_category": {
        "reasoning": "VERBATIM EXTRACTION",
        "parsing_confidence": 1.0,
        "extraction_confidence": 1.0,
        "confidence": 1.0,
        "value__": {
          "citation": [
            {
              "page": 1,
              "matching_text": "# ETH-Domain ORD Program - Measure 1 \"Contribute Projects\" - Call 4 - Deadline 31 March 2023 (17:00 CEST)",
              "bounding_boxes": [
                {
                  "x": 32.0,
                  "y": 140.0,
                  "w": 508.0,
                  "h": 77.0
                }
              ],
              "page_dimensions": {
                "width": 595.0,
                "height": 842.0
              }
            },
            {
              "page": 10,
              "matching_text": "# Track C: Contribute projects",
              "bounding_boxes": [
                {
                  "x": 69.0,
                  "y": 130.0,
                  "w": 283.0,
                  "h": 80.0
                }
              ],
              "page_dimensions": {
                "width": 595.25,
                "height": 842.0
              }
            },
            {
              "page": 22,
              "matching_text": "**ETH Domain ORD Program**\n***Contribute Track***",
              "bounding_boxes": [
                {
                  "x": 310.0,
                  "y": 141.0,
                  "w": 154.0,
                  "h": 27.0
                }
              ],
              "page_dimensions": {
                "width": 595.25,
                "height": 842.0
              }
            }
          ]
        },
        "parsing_confidence__": {
          "citation": [
            {
              "page": 8,
              "matching_text": "In addition, I took part in the implementation of a tip-sample distance control system for MFM [3], where the distance between probe and sample can be measured and controlled within 1 nm.",
              "bounding_boxes": [
                {
                  "x": 77.0,
                  "y": 154.0,
                  "w": 458.0,
                  "h": 122.0
                }
              ],
              "page_dimensions": {
                "width": 595.29998779,
                "height": 841.90002441
              }
            },
            {
              "page": 12,
              "matching_text": "**1. Project title**",
              "bounding_boxes": [
                {
                  "x": 70.0,
                  "y": 152.0,
                  "w": 79.0,
                  "h": 11.0
                }
              ],
              "page_dimensions": {
                "width": 595.25,
                "height": 842.0
              }
            },
            {
              "page": 22,
              "matching_text": "1",
              "bounding_boxes": [
                {
                  "x": 567.0,
                  "y": 798.0,
                  "w": 3.0,
                  "h": 6.0
                }
              ],
              "page_dimensions": {
                "width": 595.25,
                "height": 842.0
              }
            }
          ]
        },
        "extraction_confidence__": {
          "citation": [
            {
              "page": 8,
              "matching_text": "In addition, I took part in the implementation of a tip-sample distance control system for MFM [3], where the distance between probe and sample can be measured and controlled within 1 nm.",
              "bounding_boxes": [
                {
                  "x": 77.0,
                  "y": 154.0,
                  "w": 458.0,
                  "h": 122.0
                }
              ],
              "page_dimensions": {
                "width": 595.29998779,
                "height": 841.90002441
              }
            },
            {
              "page": 12,
              "matching_text": "**1. Project title**",
              "bounding_boxes": [
                {
                  "x": 70.0,
                  "y": 152.0,
                  "w": 79.0,
                  "h": 11.0
                }
              ],
              "page_dimensions": {
                "width": 595.25,
                "height": 842.0
              }
            },
            {
              "page": 22,
              "matching_text": "1",
              "bounding_boxes": [
                {
                  "x": 567.0,
                  "y": 798.0,
                  "w": 3.0,
                  "h": 6.0
                }
              ],
              "page_dimensions": {
                "width": 595.25,
                "height": 842.0
              }
            }
          ]
        },
        "confidence__": {
          "citation": [
            {
              "page": 8,
              "matching_text": "In addition, I took part in the implementation of a tip-sample distance control system for MFM [3], where the distance between probe and sample can be measured and controlled within 1 nm.",
              "bounding_boxes": [
                {
                  "x": 77.0,
                  "y": 154.0,
                  "w": 458.0,
                  "h": 122.0
                }
              ],
              "page_dimensions": {
                "width": 595.29998779,
                "height": 841.90002441
              }
            },
            {
              "page": 12,
              "matching_text": "**1. Project title**",
              "bounding_boxes": [
                {
                  "x": 70.0,
                  "y": 152.0,
                  "w": 79.0,
                  "h": 11.0
                }
              ],
              "page_dimensions": {
                "width": 595.25,
                "height": 842.0
              }
            },
            {
              "page": 22,
              "matching_text": "1",
              "bounding_boxes": [
                {
                  "x": 567.0,
                  "y": 798.0,
                  "w": 3.0,
                  "h": 6.0
                }
              ],
              "page_dimensions": {
                "width": 595.25,
                "height": 842.0
              }
            }
          ]
        }
      },
      "main_applicant_institution": {
        "reasoning": "VERBATIM EXTRACTION",
        "parsing_confidence": 1.0,
        "extraction_confidence": 1.0,
        "confidence": 1.0,
        "scratchpad__": {
          "citation": [
            {
              "page": 1,
              "matching_text": "| Which ETH Domain do you belong to?",
              "bounding_boxes": [
                {
                  "x": 43.0,
                  "y": 382.0,
                  "w": 186.0,
                  "h": 119.0
                }
              ],
              "page_dimensions": {
                "width": 595.0,
                "height": 842.0
              }
            }
          ]
        },
        "value__": {
          "citation": [
            {
              "page": 8,
              "matching_text": "[1] [website. ](https://www.epfl.ch/labs/lbni/openhardware/)Open Access.",
              "bounding_boxes": [
                {
                  "x": 79.0,
                  "y": 734.0,
                  "w": 89.0,
                  "h": 9.0
                }
              ],
              "page_dimensions": {
                "width": 595.29998779,
                "height": 841.90002441
              }
            },
            {
              "page": 17,
              "matching_text": "ETH BOARD\nETH zürich EPFL PAUL SCHERRER INSTITUT PSI WSL Empa Materials Science and Technology eawag aquatic research",
              "bounding_boxes": [
                {
                  "x": 556.0,
                  "y": 825.0,
                  "w": 6.0,
                  "h": 15.0
                }
              ],
              "page_dimensions": {
                "width": 595.25,
                "height": 842.0
              }
            },
            {
              "page": 20,
              "matching_text": "ETH BOARD\nETH Zürich EPFL PAUL SCHERRER INSTITUT PSI WSL Empa Materials Science and Technology eawag aquatic research",
              "bounding_boxes": [
                {
                  "x": 556.0,
                  "y": 825.0,
                  "w": 6.0,
                  "h": 15.0
                }
              ],
              "page_dimensions": {
                "width": 595.25,
                "height": 842.0
              }
            }
          ]
        },
        "parsing_confidence__": {
          "citation": [
            {
              "page": 8,
              "matching_text": "[1] [website. ](https://www.epfl.ch/labs/lbni/openhardware/)Open Access.",
              "bounding_boxes": [
                {
                  "x": 79.0,
                  "y": 734.0,
                  "w": 89.0,
                  "h": 9.0
                }
              ],
              "page_dimensions": {
                "width": 595.29998779,
                "height": 841.90002441
              }
            },
            {
              "page": 12,
              "matching_text": "**1. Project title**",
              "bounding_boxes": [
                {
                  "x": 70.0,
                  "y": 152.0,
                  "w": 79.0,
                  "h": 11.0
                }
              ],
              "page_dimensions": {
                "width": 595.25,
                "height": 842.0
              }
            },
            {
              "page": 22,
              "matching_text": "1",
              "bounding_boxes": [
                {
                  "x": 567.0,
                  "y": 798.0,
                  "w": 3.0,
                  "h": 6.0
                }
              ],
              "page_dimensions": {
                "width": 595.25,
                "height": 842.0
              }
            }
          ]
        },
        "extraction_confidence__": {
          "citation": [
            {
              "page": 8,
              "matching_text": "[1] [website. ](https://www.epfl.ch/labs/lbni/openhardware/)Open Access.",
              "bounding_boxes": [
                {
                  "x": 79.0,
                  "y": 734.0,
                  "w": 89.0,
                  "h": 9.0
                }
              ],
              "page_dimensions": {
                "width": 595.29998779,
                "height": 841.90002441
              }
            },
            {
              "page": 12,
              "matching_text": "**1. Project title**",
              "bounding_boxes": [
                {
                  "x": 70.0,
                  "y": 152.0,
                  "w": 79.0,
                  "h": 11.0
                }
              ],
              "page_dimensions": {
                "width": 595.25,
                "height": 842.0
              }
            },
            {
              "page": 22,
              "matching_text": "1",
              "bounding_boxes": [
                {
                  "x": 567.0,
                  "y": 798.0,
                  "w": 3.0,
                  "h": 6.0
                }
              ],
              "page_dimensions": {
                "width": 595.25,
                "height": 842.0
              }
            }
          ]
        },
        "confidence__": {
          "citation": [
            {
              "page": 8,
              "matching_text": "[1] [website. ](https://www.epfl.ch/labs/lbni/openhardware/)Open Access.",
              "bounding_boxes": [
                {
                  "x": 79.0,
                  "y": 734.0,
                  "w": 89.0,
                  "h": 9.0
                }
              ],
              "page_dimensions": {
                "width": 595.29998779,
                "height": 841.90002441
              }
            },
            {
              "page": 12,
              "matching_text": "**1. Project title**",
              "bounding_boxes": [
                {
                  "x": 70.0,
                  "y": 152.0,
                  "w": 79.0,
                  "h": 11.0
                }
              ],
              "page_dimensions": {
                "width": 595.25,
                "height": 842.0
              }
            },
            {
              "page": 22,
              "matching_text": "1",
              "bounding_boxes": [
                {
                  "x": 567.0,
                  "y": 798.0,
                  "w": 3.0,
                  "h": 6.0
                }
              ],
              "page_dimensions": {
                "width": 595.25,
                "height": 842.0
              }
            }
          ]
        }
      },
      "main_applicant_function": {
        "reasoning": "VERBATIM EXTRACTION",
        "parsing_confidence": 1.0,
        "extraction_confidence": 1.0,
        "confidence": 1.0,
        "value__": {
          "citation": [
            {
              "page": 1,
              "matching_text": "...| Scientist                                               |",
              "bounding_boxes": [
                {
                  "x": 43.0,
                  "y": 382.0,
                  "w": 186.0,
                  "h": 119.0
                }
              ],
              "page_dimensions": {
                "width": 595.0,
                "height": 842.0
              }
            }
          ]
        },
        "parsing_confidence__": {
          "citation": [
            {
              "page": 8,
              "matching_text": "In addition, I took part in the implementation of a tip-sample distance control system for MFM [3], where the distance between probe and sample can be measured and controlled within 1 nm.",
              "bounding_boxes": [
                {
                  "x": 77.0,
                  "y": 154.0,
                  "w": 458.0,
                  "h": 122.0
                }
              ],
              "page_dimensions": {
                "width": 595.29998779,
                "height": 841.90002441
              }
            }
          ]
        },
        "extraction_confidence__": {
          "citation": [
            {
              "page": 8,
              "matching_text": "In addition, I took part in the implementation of a tip-sample distance control system for MFM [3], where the distance between probe and sample can be measured and controlled within 1 nm.",
              "bounding_boxes": [
                {
                  "x": 77.0,
                  "y": 154.0,
                  "w": 458.0,
                  "h": 122.0
                }
              ],
              "page_dimensions": {
                "width": 595.29998779,
                "height": 841.90002441
              }
            }
          ]
        },
        "confidence__": {
          "citation": [
            {
              "page": 8,
              "matching_text": "In addition, I took part in the implementation of a tip-sample distance control system for MFM [3], where the distance between probe and sample can be measured and controlled within 1 nm.",
              "bounding_boxes": [
                {
                  "x": 77.0,
                  "y": 154.0,
                  "w": 458.0,
                  "h": 122.0
                }
              ],
              "page_dimensions": {
                "width": 595.29998779,
                "height": 841.90002441
              }
            }
          ]
        }
      },
      "main_applicant_first_name": {
        "reasoning": "VERBATIM EXTRACTION",
        "parsing_confidence": 1.0,
        "extraction_confidence": 1.0,
        "confidence": 1.0,
        "value__": {
          "citation": [
            {
              "page": 1,
              "matching_text": "Marcos Penedo Garcia | Applicant ID - ORD1000244",
              "bounding_boxes": [
                {
                  "x": 263.0,
                  "y": 40.0,
                  "w": 294.0,
                  "h": 11.0
                }
              ],
              "page_dimensions": {
                "width": 595.0,
                "height": 842.0
              }
            },
            {
              "page": 22,
              "matching_text": "Georg Fantner at Laboratory for Bio- and Nano- Instrumentation supports the application of Marcos Penedo García for an *ORD Contribute* project at EPFL for the project entitled HDF5-USID scheme implem...",
              "bounding_boxes": [
                {
                  "x": 81.0,
                  "y": 332.0,
                  "w": 439.0,
                  "h": 53.0
                }
              ],
              "page_dimensions": {
                "width": 595.25,
                "height": 842.0
              }
            }
          ]
        },
        "parsing_confidence__": {
          "citation": [
            {
              "page": 8,
              "matching_text": "In addition, I took part in the implementation of a tip-sample distance control system for MFM [3], where the distance between probe and sample can be measured and controlled within 1 nm.",
              "bounding_boxes": [
                {
                  "x": 77.0,
                  "y": 154.0,
                  "w": 458.0,
                  "h": 122.0
                }
              ],
              "page_dimensions": {
                "width": 595.29998779,
                "height": 841.90002441
              }
            },
            {
              "page": 12,
              "matching_text": "**1. Project title**",
              "bounding_boxes": [
                {
                  "x": 70.0,
                  "y": 152.0,
                  "w": 79.0,
                  "h": 11.0
                }
              ],
              "page_dimensions": {
                "width": 595.25,
                "height": 842.0
              }
            },
            {
              "page": 22,
              "matching_text": "1",
              "bounding_boxes": [
                {
                  "x": 567.0,
                  "y": 798.0,
                  "w": 3.0,
                  "h": 6.0
                }
              ],
              "page_dimensions": {
                "width": 595.25,
                "height": 842.0
              }
            }
          ]
        },
        "extraction_confidence__": {
          "citation": [
            {
              "page": 8,
              "matching_text": "In addition, I took part in the implementation of a tip-sample distance control system for MFM [3], where the distance between probe and sample can be measured and controlled within 1 nm.",
              "bounding_boxes": [
                {
                  "x": 77.0,
                  "y": 154.0,
                  "w": 458.0,
                  "h": 122.0
                }
              ],
              "page_dimensions": {
                "width": 595.29998779,
                "height": 841.90002441
              }
            },
            {
              "page": 22,
              "matching_text": "1",
              "bounding_boxes": [
                {
                  "x": 567.0,
                  "y": 798.0,
                  "w": 3.0,
                  "h": 6.0
                }
              ],
              "page_dimensions": {
                "width": 595.25,
                "height": 842.0
              }
            }
          ]
        },
        "confidence__": {
          "citation": [
            {
              "page": 8,
              "matching_text": "In addition, I took part in the implementation of a tip-sample distance control system for MFM [3], where the distance between probe and sample can be measured and controlled within 1 nm.",
              "bounding_boxes": [
                {
                  "x": 77.0,
                  "y": 154.0,
                  "w": 458.0,
                  "h": 122.0
                }
              ],
              "page_dimensions": {
                "width": 595.29998779,
                "height": 841.90002441
              }
            },
            {
              "page": 22,
              "matching_text": "1",
              "bounding_boxes": [
                {
                  "x": 567.0,
                  "y": 798.0,
                  "w": 3.0,
                  "h": 6.0
                }
              ],
              "page_dimensions": {
                "width": 595.25,
                "height": 842.0
              }
            }
          ]
        }
      },
      "main_applicant_surname": {
        "reasoning": "VERBATIM EXTRACTION",
        "parsing_confidence": 1.0,
        "extraction_confidence": 1.0,
        "confidence": 1.0,
        "value__": {
          "citation": [
            {
              "page": 1,
              "matching_text": "Marcos Penedo Garcia | Applicant ID - ORD1000244",
              "bounding_boxes": [
                {
                  "x": 263.0,
                  "y": 40.0,
                  "w": 294.0,
                  "h": 11.0
                }
              ],
              "page_dimensions": {
                "width": 595.0,
                "height": 842.0
              }
            },
            {
              "page": 22,
              "matching_text": "Georg Fantner at Laboratory for Bio- and Nano- Instrumentation supports the application of Marcos Penedo García for an *ORD Contribute* project at EPFL for the project entitled HDF5-USID scheme implem...",
              "bounding_boxes": [
                {
                  "x": 81.0,
                  "y": 332.0,
                  "w": 439.0,
                  "h": 53.0
                }
              ],
              "page_dimensions": {
                "width": 595.25,
                "height": 842.0
              }
            }
          ]
        },
        "parsing_confidence__": {
          "citation": [
            {
              "page": 6,
              "matching_text": "| Page 1/4 | 31 March 2023, Marcos Penedo Garcia, ORCID \\[iD 0000-0002-2936-7354]\\(<https://orcid.org/0000-0002-2936-7354>) |",
              "bounding_boxes": [
                {
                  "x": 52.0,
                  "y": 819.0,
                  "w": 30.0,
                  "h": 8.0
                }
              ],
              "page_dimensions": {
                "width": 595.29998779,
                "height": 841.90002441
              }
            },
            {
              "page": 12,
              "matching_text": "**1. Project title**",
              "bounding_boxes": [
                {
                  "x": 70.0,
                  "y": 152.0,
                  "w": 79.0,
                  "h": 11.0
                }
              ],
              "page_dimensions": {
                "width": 595.25,
                "height": 842.0
              }
            },
            {
              "page": 22,
              "matching_text": "1",
              "bounding_boxes": [
                {
                  "x": 567.0,
                  "y": 798.0,
                  "w": 3.0,
                  "h": 6.0
                }
              ],
              "page_dimensions": {
                "width": 595.25,
                "height": 842.0
              }
            }
          ]
        },
        "extraction_confidence__": {
          "citation": [
            {
              "page": 6,
              "matching_text": "| Page 1/4 | 31 March 2023, Marcos Penedo Garcia, ORCID \\[iD 0000-0002-2936-7354]\\(<https://orcid.org/0000-0002-2936-7354>) |",
              "bounding_boxes": [
                {
                  "x": 52.0,
                  "y": 819.0,
                  "w": 30.0,
                  "h": 8.0
                }
              ],
              "page_dimensions": {
                "width": 595.29998779,
                "height": 841.90002441
              }
            },
            {
              "page": 22,
              "matching_text": "1",
              "bounding_boxes": [
                {
                  "x": 567.0,
                  "y": 798.0,
                  "w": 3.0,
                  "h": 6.0
                }
              ],
              "page_dimensions": {
                "width": 595.25,
                "height": 842.0
              }
            }
          ]
        },
        "confidence__": {
          "citation": [
            {
              "page": 6,
              "matching_text": "| Page 1/4 | 31 March 2023, Marcos Penedo Garcia, ORCID \\[iD 0000-0002-2936-7354]\\(<https://orcid.org/0000-0002-2936-7354>) |",
              "bounding_boxes": [
                {
                  "x": 52.0,
                  "y": 819.0,
                  "w": 30.0,
                  "h": 8.0
                }
              ],
              "page_dimensions": {
                "width": 595.29998779,
                "height": 841.90002441
              }
            },
            {
              "page": 22,
              "matching_text": "1",
              "bounding_boxes": [
                {
                  "x": 567.0,
                  "y": 798.0,
                  "w": 3.0,
                  "h": 6.0
                }
              ],
              "page_dimensions": {
                "width": 595.25,
                "height": 842.0
              }
            }
          ]
        }
      },
      "main_applicant_laboratory_name": {
        "reasoning": "Combined the table's formal EPFL unit designation and the full laboratory name from the supporting letter, as they refer to the same entity (LBNI, EPFL). The two sources (table and letter) are merged for best clarity and exhaustiveness. Confidence score is the average of the two sources' confidence scores.",
        "parsing_confidence": 1.0,
        "extraction_confidence": 0.9960496239869142,
        "confidence": 0.9960496239869142,
        "scratchpad__": {
          "citation": [
            {
              "page": 1,
              "matching_text": "| EPFL Laboratory...",
              "bounding_boxes": [
                {
                  "x": 43.0,
                  "y": 382.0,
                  "w": 186.0,
                  "h": 119.0
                }
              ],
              "page_dimensions": {
                "width": 595.0,
                "height": 842.0
              }
            },
            {
              "page": 22,
              "matching_text": "This letter thereby confirms that Marcos Penedo García is fully entitled to execute the above-mentioned project in the Laboratory for Bio- and Nano- Instrumentation, headed by Georg Fantner.",
              "bounding_boxes": [
                {
                  "x": 81.0,
                  "y": 402.0,
                  "w": 439.0,
                  "h": 91.0
                }
              ],
              "page_dimensions": {
                "width": 595.25,
                "height": 842.0
              }
            }
          ]
        },
        "value__": {
          "citation": [
            {
              "page": 1,
              "matching_text": "...| EPFL STI IBI-STI LBNI                                   |",
              "bounding_boxes": [
                {
                  "x": 43.0,
                  "y": 382.0,
                  "w": 186.0,
                  "h": 119.0
                }
              ],
              "page_dimensions": {
                "width": 595.0,
                "height": 842.0
              }
            },
            {
              "page": 22,
              "matching_text": "Georg Fantner at Laboratory for Bio- and Nano- Instrumentation supports the application of Marcos Penedo García for an *ORD Contribute* project at EPFL for the project entitled HDF5-USID scheme implem...",
              "bounding_boxes": [
                {
                  "x": 81.0,
                  "y": 332.0,
                  "w": 439.0,
                  "h": 53.0
                }
              ],
              "page_dimensions": {
                "width": 595.25,
                "height": 842.0
              }
            }
          ]
        },
        "parsing_confidence__": {
          "citation": [
            {
              "page": 8,
              "matching_text": "[1] [website. ](https://www.epfl.ch/labs/lbni/openhardware/)Open Access.",
              "bounding_boxes": [
                {
                  "x": 79.0,
                  "y": 734.0,
                  "w": 89.0,
                  "h": 9.0
                }
              ],
              "page_dimensions": {
                "width": 595.29998779,
                "height": 841.90002441
              }
            },
            {
              "page": 22,
              "matching_text": "1",
              "bounding_boxes": [
                {
                  "x": 567.0,
                  "y": 798.0,
                  "w": 3.0,
                  "h": 6.0
                }
              ],
              "page_dimensions": {
                "width": 595.25,
                "height": 842.0
              }
            }
          ]
        },
        "extraction_confidence__": {
          "citation": [
            {
              "page": 8,
              "matching_text": "[1] [website. ](https://www.epfl.ch/labs/lbni/openhardware/)Open Access.",
              "bounding_boxes": [
                {
                  "x": 79.0,
                  "y": 734.0,
                  "w": 89.0,
                  "h": 9.0
                }
              ],
              "page_dimensions": {
                "width": 595.29998779,
                "height": 841.90002441
              }
            }
          ]
        },
        "confidence__": {
          "citation": [
            {
              "page": 8,
              "matching_text": "[1] [website. ](https://www.epfl.ch/labs/lbni/openhardware/)Open Access.",
              "bounding_boxes": [
                {
                  "x": 79.0,
                  "y": 734.0,
                  "w": 89.0,
                  "h": 9.0
                }
              ],
              "page_dimensions": {
                "width": 595.29998779,
                "height": 841.90002441
              }
            }
          ]
        }
      },
      "main_applicant_postcode": {
        "reasoning": "VERBATIM EXTRACTION",
        "parsing_confidence": 1.0,
        "extraction_confidence": 1.0,
        "confidence": 1.0,
        "value__": {
          "citation": [
            {
              "page": 1,
              "matching_text": "...| 1015                                                    |",
              "bounding_boxes": [
                {
                  "x": 275.0,
                  "y": 560.0,
                  "w": 44.0,
                  "h": 25.0
                }
              ],
              "page_dimensions": {
                "width": 595.0,
                "height": 842.0
              }
            },
            {
              "page": 19,
              "matching_text": "| EPFL Research Office | EPFL VPA AVP-R<br/>Station 7<br/>CH - 1015 Lausanne | +4121 693 49 28<br/><research@epfl.ch> | P<br/>A |",
              "bounding_boxes": [
                {
                  "x": 55.0,
                  "y": 800.0,
                  "w": 83.0,
                  "h": 7.0
                }
              ],
              "page_dimensions": {
                "width": 595.25,
                "height": 842.0
              }
            }
          ]
        },
        "parsing_confidence__": {
          "citation": [
            {
              "page": 8,
              "matching_text": "In addition, I took part in the implementation of a tip-sample distance control system for MFM [3], where the distance between probe and sample can be measured and controlled within 1 nm.",
              "bounding_boxes": [
                {
                  "x": 77.0,
                  "y": 154.0,
                  "w": 458.0,
                  "h": 122.0
                }
              ],
              "page_dimensions": {
                "width": 595.29998779,
                "height": 841.90002441
              }
            },
            {
              "page": 22,
              "matching_text": "1",
              "bounding_boxes": [
                {
                  "x": 567.0,
                  "y": 798.0,
                  "w": 3.0,
                  "h": 6.0
                }
              ],
              "page_dimensions": {
                "width": 595.25,
                "height": 842.0
              }
            }
          ]
        },
        "extraction_confidence__": {
          "citation": [
            {
              "page": 8,
              "matching_text": "In addition, I took part in the implementation of a tip-sample distance control system for MFM [3], where the distance between probe and sample can be measured and controlled within 1 nm.",
              "bounding_boxes": [
                {
                  "x": 77.0,
                  "y": 154.0,
                  "w": 458.0,
                  "h": 122.0
                }
              ],
              "page_dimensions": {
                "width": 595.29998779,
                "height": 841.90002441
              }
            },
            {
              "page": 22,
              "matching_text": "1",
              "bounding_boxes": [
                {
                  "x": 567.0,
                  "y": 798.0,
                  "w": 3.0,
                  "h": 6.0
                }
              ],
              "page_dimensions": {
                "width": 595.25,
                "height": 842.0
              }
            }
          ]
        },
        "confidence__": {
          "citation": [
            {
              "page": 8,
              "matching_text": "In addition, I took part in the implementation of a tip-sample distance control system for MFM [3], where the distance between probe and sample can be measured and controlled within 1 nm.",
              "bounding_boxes": [
                {
                  "x": 77.0,
                  "y": 154.0,
                  "w": 458.0,
                  "h": 122.0
                }
              ],
              "page_dimensions": {
                "width": 595.29998779,
                "height": 841.90002441
              }
            },
            {
              "page": 22,
              "matching_text": "1",
              "bounding_boxes": [
                {
                  "x": 567.0,
                  "y": 798.0,
                  "w": 3.0,
                  "h": 6.0
                }
              ],
              "page_dimensions": {
                "width": 595.25,
                "height": 842.0
              }
            }
          ]
        }
      },
      "main_applicant_city": {
        "reasoning": "VERBATIM EXTRACTION",
        "parsing_confidence": 1.0,
        "extraction_confidence": 1.0,
        "confidence": 1.0,
        "value__": {
          "citation": [
            {
              "page": 6,
              "matching_text": "| Research associate / Scientific collaborator<br/>Georg Fantner | EPF Lausanne - EPFL, CH<br/>Laboratory for Bio- and Nano-Instrumentation | 08.2020 - Present<br/>2 year(s) 8 month(s) |",
              "bounding_boxes": [
                {
                  "x": 78.0,
                  "y": 658.0,
                  "w": 452.0,
                  "h": 104.0
                }
              ],
              "page_dimensions": {
                "width": 595.29998779,
                "height": 841.90002441
              }
            },
            {
              "page": 22,
              "matching_text": "Lausanne, March 31<sup>st</sup>, 2023",
              "bounding_boxes": [
                {
                  "x": 309.0,
                  "y": 220.0,
                  "w": 150.0,
                  "h": 11.0
                }
              ],
              "page_dimensions": {
                "width": 595.25,
                "height": 842.0
              }
            }
          ]
        },
        "parsing_confidence__": {
          "citation": [
            {
              "page": 8,
              "matching_text": "In addition, I took part in the implementation of a tip-sample distance control system for MFM [3], where the distance between probe and sample can be measured and controlled within 1 nm.",
              "bounding_boxes": [
                {
                  "x": 77.0,
                  "y": 154.0,
                  "w": 458.0,
                  "h": 122.0
                }
              ],
              "page_dimensions": {
                "width": 595.29998779,
                "height": 841.90002441
              }
            },
            {
              "page": 22,
              "matching_text": "1",
              "bounding_boxes": [
                {
                  "x": 567.0,
                  "y": 798.0,
                  "w": 3.0,
                  "h": 6.0
                }
              ],
              "page_dimensions": {
                "width": 595.25,
                "height": 842.0
              }
            }
          ]
        },
        "extraction_confidence__": {
          "citation": [
            {
              "page": 8,
              "matching_text": "In addition, I took part in the implementation of a tip-sample distance control system for MFM [3], where the distance between probe and sample can be measured and controlled within 1 nm.",
              "bounding_boxes": [
                {
                  "x": 77.0,
                  "y": 154.0,
                  "w": 458.0,
                  "h": 122.0
                }
              ],
              "page_dimensions": {
                "width": 595.29998779,
                "height": 841.90002441
              }
            },
            {
              "page": 22,
              "matching_text": "1",
              "bounding_boxes": [
                {
                  "x": 567.0,
                  "y": 798.0,
                  "w": 3.0,
                  "h": 6.0
                }
              ],
              "page_dimensions": {
                "width": 595.25,
                "height": 842.0
              }
            }
          ]
        },
        "confidence__": {
          "citation": [
            {
              "page": 8,
              "matching_text": "In addition, I took part in the implementation of a tip-sample distance control system for MFM [3], where the distance between probe and sample can be measured and controlled within 1 nm.",
              "bounding_boxes": [
                {
                  "x": 77.0,
                  "y": 154.0,
                  "w": 458.0,
                  "h": 122.0
                }
              ],
              "page_dimensions": {
                "width": 595.29998779,
                "height": 841.90002441
              }
            },
            {
              "page": 22,
              "matching_text": "1",
              "bounding_boxes": [
                {
                  "x": 567.0,
                  "y": 798.0,
                  "w": 3.0,
                  "h": 6.0
                }
              ],
              "page_dimensions": {
                "width": 595.25,
                "height": 842.0
              }
            }
          ]
        }
      },
      "all_applicants": [
        {
          "eth_domain_institution": {
            "parsing_confidence": 1.0,
            "extraction_confidence": 1.0,
            "confidence": 1.0
          },
          "function_title": {
            "parsing_confidence": 1.0,
            "extraction_confidence": 1.0,
            "confidence": 1.0
          },
          "first_name": {
            "parsing_confidence": 1.0,
            "extraction_confidence": 1.0,
            "confidence": 1.0
          },
          "surname": {
            "parsing_confidence": 1.0,
            "extraction_confidence": 1.0,
            "confidence": 1.0
          },
          "postcode": {
            "parsing_confidence": 1.0,
            "extraction_confidence": 1.0,
            "confidence": 1.0
          },
          "reasoning": "VERBATIM EXTRACTION"
        }
      ],
      "project_title": {
        "reasoning": "The strictly verbatim project title, as presented in the RESEARCH PROPOSAL section (pages 2 and 12), is taken as definitive. Although a similar but expanded wording appears in the letter of support, document structure and location preference means the proposal body's text is primary. Confidence is averaged between the two high-confidence, matching extractions.",
        "parsing_confidence": 1.0,
        "extraction_confidence": 0.9999999951596839,
        "confidence": 0.9999999951596839,
        "scratchpad__": {
          "citation": [
            {
              "page": 2,
              "matching_text": "| Project title...",
              "bounding_boxes": [
                {
                  "x": 275.0,
                  "y": 99.0,
                  "w": 252.0,
                  "h": 39.0
                }
              ],
              "page_dimensions": {
                "width": 595.0,
                "height": 842.0
              }
            },
            {
              "page": 12,
              "matching_text": "> HDF5-USID scheme implementation in the Open-Source SPM project for Pycroscopy ecosystems",
              "bounding_boxes": [
                {
                  "x": 70.0,
                  "y": 174.0,
                  "w": 466.0,
                  "h": 31.0
                }
              ],
              "page_dimensions": {
                "width": 595.25,
                "height": 842.0
              }
            },
            {
              "page": 22,
              "matching_text": "Georg Fantner at Laboratory for Bio- and Nano- Instrumentation supports the application of Marcos Penedo García for an *ORD Contribute* project at EPFL for the project entitled HDF5-USID scheme imp...",
              "bounding_boxes": [
                {
                  "x": 81.0,
                  "y": 332.0,
                  "w": 439.0,
                  "h": 53.0
                }
              ],
              "page_dimensions": {
                "width": 595.25,
                "height": 842.0
              }
            }
          ]
        },
        "value__": {
          "citation": [
            {
              "page": 2,
              "matching_text": "...| HDF5-USID scheme implementation in the Open-Source SPM project for Pycroscopy ecosystems...",
              "bounding_boxes": [
                {
                  "x": 275.0,
                  "y": 99.0,
                  "w": 252.0,
                  "h": 39.0
                }
              ],
              "page_dimensions": {
                "width": 595.0,
                "height": 842.0
              }
            },
            {
              "page": 12,
              "matching_text": "> HDF5-USID scheme implementation in the Open-Source SPM project for Pycroscopy ecosystems",
              "bounding_boxes": [
                {
                  "x": 70.0,
                  "y": 174.0,
                  "w": 466.0,
                  "h": 31.0
                }
              ],
              "page_dimensions": {
                "width": 595.25,
                "height": 842.0
              }
            },
            {
              "page": 22,
              "matching_text": "...pplication of Marcos Penedo García for an *ORD Contribute* project at EPFL for the project entitled HDF5-USID scheme implementation in the Open-Source SPM controller enabling Pycroscopy ecosystem, pen...",
              "bounding_boxes": [
                {
                  "x": 81.0,
                  "y": 332.0,
                  "w": 439.0,
                  "h": 53.0
                }
              ],
              "page_dimensions": {
                "width": 595.25,
                "height": 842.0
              }
            }
          ]
        },
        "parsing_confidence__": {
          "citation": [
            {
              "page": 8,
              "matching_text": "In addition, I took part in the implementation of a tip-sample distance control system for MFM [3], where the distance between probe and sample can be measured and controlled within 1 nm.",
              "bounding_boxes": [
                {
                  "x": 77.0,
                  "y": 154.0,
                  "w": 458.0,
                  "h": 122.0
                }
              ],
              "page_dimensions": {
                "width": 595.29998779,
                "height": 841.90002441
              }
            },
            {
              "page": 12,
              "matching_text": "**1. Project title**",
              "bounding_boxes": [
                {
                  "x": 70.0,
                  "y": 152.0,
                  "w": 79.0,
                  "h": 11.0
                }
              ],
              "page_dimensions": {
                "width": 595.25,
                "height": 842.0
              }
            },
            {
              "page": 22,
              "matching_text": "1",
              "bounding_boxes": [
                {
                  "x": 567.0,
                  "y": 798.0,
                  "w": 3.0,
                  "h": 6.0
                }
              ],
              "page_dimensions": {
                "width": 595.25,
                "height": 842.0
              }
            }
          ]
        },
        "extraction_confidence__": {
          "citation": [
            {
              "page": 12,
              "matching_text": "**1. Project title**",
              "bounding_boxes": [
                {
                  "x": 70.0,
                  "y": 152.0,
                  "w": 79.0,
                  "h": 11.0
                }
              ],
              "page_dimensions": {
                "width": 595.25,
                "height": 842.0
              }
            }
          ]
        },
        "confidence__": {
          "citation": [
            {
              "page": 12,
              "matching_text": "**1. Project title**",
              "bounding_boxes": [
                {
                  "x": 70.0,
                  "y": 152.0,
                  "w": 79.0,
                  "h": 11.0
                }
              ],
              "page_dimensions": {
                "width": 595.25,
                "height": 842.0
              }
            }
          ]
        }
      },
      "project_acronym": {
        "reasoning": "VERBATIM EXTRACTION",
        "parsing_confidence": 1.0,
        "extraction_confidence": 0.9999999677312261,
        "confidence": 0.9999999677312261,
        "value__": {
          "citation": [
            {
              "page": 2,
              "matching_text": "...| PySPM...",
              "bounding_boxes": [
                {
                  "x": 44.0,
                  "y": 149.0,
                  "w": 42.0,
                  "h": 13.0
                }
              ],
              "page_dimensions": {
                "width": 595.0,
                "height": 842.0
              }
            },
            {
              "page": 12,
              "matching_text": "> \n> Acronym : PySPM",
              "bounding_boxes": [
                {
                  "x": 71.0,
                  "y": 222.0,
                  "w": 94.0,
                  "h": 12.0
                }
              ],
              "page_dimensions": {
                "width": 595.25,
                "height": 842.0
              }
            }
          ]
        },
        "parsing_confidence__": {
          "citation": [
            {
              "page": 8,
              "matching_text": "[1] [website. ](https://www.epfl.ch/labs/lbni/openhardware/)Open Access.",
              "bounding_boxes": [
                {
                  "x": 79.0,
                  "y": 734.0,
                  "w": 89.0,
                  "h": 9.0
                }
              ],
              "page_dimensions": {
                "width": 595.29998779,
                "height": 841.90002441
              }
            },
            {
              "page": 12,
              "matching_text": "**1. Project title**",
              "bounding_boxes": [
                {
                  "x": 70.0,
                  "y": 152.0,
                  "w": 79.0,
                  "h": 11.0
                }
              ],
              "page_dimensions": {
                "width": 595.25,
                "height": 842.0
              }
            }
          ]
        },
        "extraction_confidence__": {
          "citation": [
            {
              "page": 8,
              "matching_text": "[1] [website. ](https://www.epfl.ch/labs/lbni/openhardware/)Open Access.",
              "bounding_boxes": [
                {
                  "x": 79.0,
                  "y": 734.0,
                  "w": 89.0,
                  "h": 9.0
                }
              ],
              "page_dimensions": {
                "width": 595.29998779,
                "height": 841.90002441
              }
            }
          ]
        },
        "confidence__": {
          "citation": [
            {
              "page": 8,
              "matching_text": "[1] [website. ](https://www.epfl.ch/labs/lbni/openhardware/)Open Access.",
              "bounding_boxes": [
                {
                  "x": 79.0,
                  "y": 734.0,
                  "w": 89.0,
                  "h": 9.0
                }
              ],
              "page_dimensions": {
                "width": 595.29998779,
                "height": 841.90002441
              }
            }
          ]
        }
      },
      "project_abstract": {
        "reasoning": "VERBATIM EXTRACTION. The abstract from the 'RESEARCH PROPOSAL' section (document index 0, page 2) is directly labeled and covers the requirements for a project abstract; the second instance is a background summary that largely repeats the same content.",
        "parsing_confidence": 1.0,
        "extraction_confidence": 0.9999999550062165,
        "confidence": 0.9999999550062165,
        "scratchpad__": {
          "citation": [
            {
              "page": 2,
              "matching_text": "Furthermore, the implementation of this scheme will enable the access to a lively open software ecosystem called Pycroscopy, where the Open-Source SPM project will take advantage of all the functio...",
              "bounding_boxes": [
                {
                  "x": 43.0,
                  "y": 173.0,
                  "w": 501.0,
                  "h": 97.0
                }
              ],
              "page_dimensions": {
                "width": 595.0,
                "height": 842.0
              }
            }
          ]
        },
        "value__": {
          "citation": [
            {
              "page": 2,
              "matching_text": "Furthermore, the implementation of this scheme will enable the access to a lively open software ecosystem called Pycroscopy, where the Open-Source SPM project will take advantage of all the functio...",
              "bounding_boxes": [
                {
                  "x": 43.0,
                  "y": 173.0,
                  "w": 501.0,
                  "h": 97.0
                }
              ],
              "page_dimensions": {
                "width": 595.0,
                "height": 842.0
              }
            },
            {
              "page": 13,
              "matching_text": "Updating its data file structure to a more modern and more aligned to ORD practices as HDF5-USID, the Open-Source SPM could take advantage of all the functionalities already existing on the Pycrosc...",
              "bounding_boxes": [
                {
                  "x": 71.0,
                  "y": 498.0,
                  "w": 466.0,
                  "h": 89.0
                }
              ],
              "page_dimensions": {
                "width": 595.25,
                "height": 842.0
              }
            }
          ]
        },
        "parsing_confidence__": {
          "citation": [
            {
              "page": 8,
              "matching_text": "[1] [website. ](https://www.epfl.ch/labs/lbni/openhardware/)Open Access.",
              "bounding_boxes": [
                {
                  "x": 79.0,
                  "y": 734.0,
                  "w": 89.0,
                  "h": 9.0
                }
              ],
              "page_dimensions": {
                "width": 595.29998779,
                "height": 841.90002441
              }
            },
            {
              "page": 12,
              "matching_text": "**1. Project title**",
              "bounding_boxes": [
                {
                  "x": 70.0,
                  "y": 152.0,
                  "w": 79.0,
                  "h": 11.0
                }
              ],
              "page_dimensions": {
                "width": 595.25,
                "height": 842.0
              }
            }
          ]
        }
      },
      "keywords": [
        {
          "reasoning": "VERBATIM EXTRACTION",
          "parsing_confidence": 1.0,
          "extraction_confidence": 1.0,
          "confidence": 1.0,
          "scratchpad__": {
            "citation": [
              {
                "page": 2,
                "matching_text": "| HDF5, USID, Pycroscopy, SPM, Open-Hardware...",
                "bounding_boxes": [
                  {
                    "x": 44.0,
                    "y": 313.0,
                    "w": 219.0,
                    "h": 11.0
                  }
                ],
                "page_dimensions": {
                  "width": 595.0,
                  "height": 842.0
                }
              }
            ]
          },
          "value__": {
            "citation": [
              {
                "page": 2,
                "matching_text": "| HDF5, USID, Pycroscopy, SPM, Open-Hardware...",
                "bounding_boxes": [
                  {
                    "x": 44.0,
                    "y": 313.0,
                    "w": 219.0,
                    "h": 11.0
                  }
                ],
                "page_dimensions": {
                  "width": 595.0,
                  "height": 842.0
                }
              }
            ]
          },
          "parsing_confidence__": {
            "citation": [
              {
                "page": 8,
                "matching_text": "[1] [website. ](https://www.epfl.ch/labs/lbni/openhardware/)Open Access.",
                "bounding_boxes": [
                  {
                    "x": 79.0,
                    "y": 734.0,
                    "w": 89.0,
                    "h": 9.0
                  }
                ],
                "page_dimensions": {
                  "width": 595.29998779,
                  "height": 841.90002441
                }
              }
            ]
          },
          "extraction_confidence__": {
            "citation": [
              {
                "page": 8,
                "matching_text": "[1] [website. ](https://www.epfl.ch/labs/lbni/openhardware/)Open Access.",
                "bounding_boxes": [
                  {
                    "x": 79.0,
                    "y": 734.0,
                    "w": 89.0,
                    "h": 9.0
                  }
                ],
                "page_dimensions": {
                  "width": 595.29998779,
                  "height": 841.90002441
                }
              }
            ]
          },
          "confidence__": {
            "citation": [
              {
                "page": 8,
                "matching_text": "[1] [website. ](https://www.epfl.ch/labs/lbni/openhardware/)Open Access.",
                "bounding_boxes": [
                  {
                    "x": 79.0,
                    "y": 734.0,
                    "w": 89.0,
                    "h": 9.0
                  }
                ],
                "page_dimensions": {
                  "width": 595.29998779,
                  "height": 841.90002441
                }
              }
            ]
          }
        },
        {
          "reasoning": "VERBATIM EXTRACTION",
          "parsing_confidence": 1.0,
          "extraction_confidence": 1.0,
          "confidence": 1.0,
          "value__": {
            "citation": [
              {
                "page": 2,
                "matching_text": "In this project, we aim to implement the HDF5 and USID open standards on an already well-established ORD worldwide project at EPFL: the Open-Source SPM controller.",
                "bounding_boxes": [
                  {
                    "x": 43.0,
                    "y": 173.0,
                    "w": 501.0,
                    "h": 97.0
                  }
                ],
                "page_dimensions": {
                  "width": 595.0,
                  "height": 842.0
                }
              }
            ]
          },
          "parsing_confidence__": {
            "citation": [
              {
                "page": 8,
                "matching_text": "[1] [website. ](https://www.epfl.ch/labs/lbni/openhardware/)Open Access.",
                "bounding_boxes": [
                  {
                    "x": 79.0,
                    "y": 734.0,
                    "w": 89.0,
                    "h": 9.0
                  }
                ],
                "page_dimensions": {
                  "width": 595.29998779,
                  "height": 841.90002441
                }
              }
            ]
          },
          "extraction_confidence__": {
            "citation": [
              {
                "page": 8,
                "matching_text": "[1] [website. ](https://www.epfl.ch/labs/lbni/openhardware/)Open Access.",
                "bounding_boxes": [
                  {
                    "x": 79.0,
                    "y": 734.0,
                    "w": 89.0,
                    "h": 9.0
                  }
                ],
                "page_dimensions": {
                  "width": 595.29998779,
                  "height": 841.90002441
                }
              }
            ]
          },
          "confidence__": {
            "citation": [
              {
                "page": 8,
                "matching_text": "[1] [website. ](https://www.epfl.ch/labs/lbni/openhardware/)Open Access.",
                "bounding_boxes": [
                  {
                    "x": 79.0,
                    "y": 734.0,
                    "w": 89.0,
                    "h": 9.0
                  }
                ],
                "page_dimensions": {
                  "width": 595.29998779,
                  "height": 841.90002441
                }
              }
            ]
          }
        },
        {
          "reasoning": "VERBATIM EXTRACTION",
          "parsing_confidence": 1.0,
          "extraction_confidence": 1.0,
          "confidence": 1.0,
          "value__": {
            "citation": [
              {
                "page": 2,
                "matching_text": "...the implementation of this scheme will enable the access to a lively open software ecosystem called Pycroscopy, where the Open-Source SPM project will take advantage of all the functionalities and too...",
                "bounding_boxes": [
                  {
                    "x": 43.0,
                    "y": 173.0,
                    "w": 501.0,
                    "h": 97.0
                  }
                ],
                "page_dimensions": {
                  "width": 595.0,
                  "height": 842.0
                }
              }
            ]
          },
          "parsing_confidence__": {
            "citation": [
              {
                "page": 8,
                "matching_text": "[1] [website. ](https://www.epfl.ch/labs/lbni/openhardware/)Open Access.",
                "bounding_boxes": [
                  {
                    "x": 79.0,
                    "y": 734.0,
                    "w": 89.0,
                    "h": 9.0
                  }
                ],
                "page_dimensions": {
                  "width": 595.29998779,
                  "height": 841.90002441
                }
              }
            ]
          },
          "extraction_confidence__": {
            "citation": [
              {
                "page": 8,
                "matching_text": "[1] [website. ](https://www.epfl.ch/labs/lbni/openhardware/)Open Access.",
                "bounding_boxes": [
                  {
                    "x": 79.0,
                    "y": 734.0,
                    "w": 89.0,
                    "h": 9.0
                  }
                ],
                "page_dimensions": {
                  "width": 595.29998779,
                  "height": 841.90002441
                }
              }
            ]
          },
          "confidence__": {
            "citation": [
              {
                "page": 8,
                "matching_text": "[1] [website. ](https://www.epfl.ch/labs/lbni/openhardware/)Open Access.",
                "bounding_boxes": [
                  {
                    "x": 79.0,
                    "y": 734.0,
                    "w": 89.0,
                    "h": 9.0
                  }
                ],
                "page_dimensions": {
                  "width": 595.29998779,
                  "height": 841.90002441
                }
              }
            ]
          }
        },
        {
          "reasoning": "VERBATIM EXTRACTION",
          "parsing_confidence": 1.0,
          "extraction_confidence": 1.0,
          "confidence": 1.0,
          "value__": {
            "citation": [
              {
                "page": 8,
                "matching_text": "Design and development of the software for the open source SPM controller project [1], a platform that has already been adapted to control different scanning probe microscopes such as atomic force mic...",
                "bounding_boxes": [
                  {
                    "x": 78.0,
                    "y": 540.0,
                    "w": 459.0,
                    "h": 179.0
                  }
                ],
                "page_dimensions": {
                  "width": 595.29998779,
                  "height": 841.90002441
                }
              }
            ]
          },
          "parsing_confidence__": {
            "citation": [
              {
                "page": 8,
                "matching_text": "Design and development of the software for the open source SPM controller project [1], a platform that has already been adapted to control different scanning probe microscopes such as atomic force...",
                "bounding_boxes": [
                  {
                    "x": 78.0,
                    "y": 540.0,
                    "w": 459.0,
                    "h": 179.0
                  }
                ],
                "page_dimensions": {
                  "width": 595.29998779,
                  "height": 841.90002441
                }
              }
            ]
          },
          "extraction_confidence__": {
            "citation": [
              {
                "page": 8,
                "matching_text": "Design and development of the software for the open source SPM controller project [1], a platform that has already been adapted to control different scanning probe microscopes such as atomic force...",
                "bounding_boxes": [
                  {
                    "x": 78.0,
                    "y": 540.0,
                    "w": 459.0,
                    "h": 179.0
                  }
                ],
                "page_dimensions": {
                  "width": 595.29998779,
                  "height": 841.90002441
                }
              }
            ]
          },
          "confidence__": {
            "citation": [
              {
                "page": 8,
                "matching_text": "Design and development of the software for the open source SPM controller project [1], a platform that has already been adapted to control different scanning probe microscopes such as atomic force...",
                "bounding_boxes": [
                  {
                    "x": 78.0,
                    "y": 540.0,
                    "w": 459.0,
                    "h": 179.0
                  }
                ],
                "page_dimensions": {
                  "width": 595.29998779,
                  "height": 841.90002441
                }
              }
            ]
          }
        },
        {
          "reasoning": "VERBATIM EXTRACTION",
          "parsing_confidence": 1.0,
          "extraction_confidence": 1.0,
          "confidence": 1.0,
          "value__": {
            "citation": [
              {
                "page": 2,
                "matching_text": "| HDF5, USID, Pycroscopy, SPM, Open-Hardware...",
                "bounding_boxes": [
                  {
                    "x": 44.0,
                    "y": 313.0,
                    "w": 219.0,
                    "h": 11.0
                  }
                ],
                "page_dimensions": {
                  "width": 595.0,
                  "height": 842.0
                }
              }
            ]
          },
          "parsing_confidence__": {
            "citation": [
              {
                "page": 8,
                "matching_text": "[1] journal-article.",
                "bounding_boxes": [
                  {
                    "x": 79.0,
                    "y": 365.0,
                    "w": 455.0,
                    "h": 76.0
                  }
                ],
                "page_dimensions": {
                  "width": 595.29998779,
                  "height": 841.90002441
                }
              }
            ]
          },
          "extraction_confidence__": {
            "citation": [
              {
                "page": 8,
                "matching_text": "[1] journal-article.",
                "bounding_boxes": [
                  {
                    "x": 79.0,
                    "y": 365.0,
                    "w": 455.0,
                    "h": 76.0
                  }
                ],
                "page_dimensions": {
                  "width": 595.29998779,
                  "height": 841.90002441
                }
              }
            ]
          },
          "confidence__": {
            "citation": [
              {
                "page": 8,
                "matching_text": "[1] journal-article.",
                "bounding_boxes": [
                  {
                    "x": 79.0,
                    "y": 365.0,
                    "w": 455.0,
                    "h": 76.0
                  }
                ],
                "page_dimensions": {
                  "width": 595.29998779,
                  "height": 841.90002441
                }
              }
            ]
          }
        }
      ],
      "start_date": {
        "reasoning": "VERBATIM EXTRACTION",
        "parsing_confidence": 1.0,
        "extraction_confidence": 1.0,
        "confidence": 1.0,
        "scratchpad__": {
          "citation": [
            {
              "page": 2,
              "matching_text": "| Proposed Starting Date...",
              "bounding_boxes": [
                {
                  "x": 44.0,
                  "y": 336.0,
                  "w": 113.0,
                  "h": 43.0
                }
              ],
              "page_dimensions": {
                "width": 595.0,
                "height": 842.0
              }
            }
          ]
        },
        "value__": {
          "citation": [
            {
              "page": 2,
              "matching_text": "| Proposed Starting Date...",
              "bounding_boxes": [
                {
                  "x": 44.0,
                  "y": 336.0,
                  "w": 113.0,
                  "h": 43.0
                }
              ],
              "page_dimensions": {
                "width": 595.0,
                "height": 842.0
              }
            }
          ]
        },
        "parsing_confidence__": {
          "citation": [
            {
              "page": 8,
              "matching_text": "[1] [website. ](https://www.epfl.ch/labs/lbni/openhardware/)Open Access.",
              "bounding_boxes": [
                {
                  "x": 79.0,
                  "y": 734.0,
                  "w": 89.0,
                  "h": 9.0
                }
              ],
              "page_dimensions": {
                "width": 595.29998779,
                "height": 841.90002441
              }
            }
          ]
        },
        "extraction_confidence__": {
          "citation": [
            {
              "page": 8,
              "matching_text": "[1] [website. ](https://www.epfl.ch/labs/lbni/openhardware/)Open Access.",
              "bounding_boxes": [
                {
                  "x": 79.0,
                  "y": 734.0,
                  "w": 89.0,
                  "h": 9.0
                }
              ],
              "page_dimensions": {
                "width": 595.29998779,
                "height": 841.90002441
              }
            }
          ]
        },
        "confidence__": {
          "citation": [
            {
              "page": 8,
              "matching_text": "[1] [website. ](https://www.epfl.ch/labs/lbni/openhardware/)Open Access.",
              "bounding_boxes": [
                {
                  "x": 79.0,
                  "y": 734.0,
                  "w": 89.0,
                  "h": 9.0
                }
              ],
              "page_dimensions": {
                "width": 595.29998779,
                "height": 841.90002441
              }
            }
          ]
        }
      },
      "project_duration_months": {
        "reasoning": "VERBATIM EXTRACTION",
        "parsing_confidence": 1.0,
        "extraction_confidence": 1.0,
        "confidence": 1.0,
        "scratchpad__": {
          "citation": [
            {
              "page": 8,
              "matching_text": "Design and development of the software for the open source SPM controller project [1], a platform that has already been adapted to control different scanning probe microscopes such as atomic force...",
              "bounding_boxes": [
                {
                  "x": 78.0,
                  "y": 540.0,
                  "w": 459.0,
                  "h": 179.0
                }
              ],
              "page_dimensions": {
                "width": 595.29998779,
                "height": 841.90002441
              }
            }
          ]
        },
        "value__": {
          "citation": [
            {
              "page": 5,
              "matching_text": "# 6 - SUBMISSION",
              "bounding_boxes": [
                {
                  "x": 32.0,
                  "y": 340.0,
                  "w": 132.0,
                  "h": 14.0
                }
              ],
              "page_dimensions": {
                "width": 595.0,
                "height": 842.0
              }
            }
          ]
        },
        "parsing_confidence__": {
          "citation": [
            {
              "page": 8,
              "matching_text": "In addition, I took part in the implementation of a tip-sample distance control system for MFM [3], where the distance between probe and sample can be measured and controlled within 1 nm.",
              "bounding_boxes": [
                {
                  "x": 77.0,
                  "y": 154.0,
                  "w": 458.0,
                  "h": 122.0
                }
              ],
              "page_dimensions": {
                "width": 595.29998779,
                "height": 841.90002441
              }
            }
          ]
        },
        "extraction_confidence__": {
          "citation": [
            {
              "page": 8,
              "matching_text": "In addition, I took part in the implementation of a tip-sample distance control system for MFM [3], where the distance between probe and sample can be measured and controlled within 1 nm.",
              "bounding_boxes": [
                {
                  "x": 77.0,
                  "y": 154.0,
                  "w": 458.0,
                  "h": 122.0
                }
              ],
              "page_dimensions": {
                "width": 595.29998779,
                "height": 841.90002441
              }
            }
          ]
        },
        "confidence__": {
          "citation": [
            {
              "page": 8,
              "matching_text": "In addition, I took part in the implementation of a tip-sample distance control system for MFM [3], where the distance between probe and sample can be measured and controlled within 1 nm.",
              "bounding_boxes": [
                {
                  "x": 77.0,
                  "y": 154.0,
                  "w": 458.0,
                  "h": 122.0
                }
              ],
              "page_dimensions": {
                "width": 595.29998779,
                "height": 841.90002441
              }
            }
          ]
        }
      },
      "total_budget_requested": {
        "reasoning": "VERBATIM EXTRACTION",
        "parsing_confidence": 1.0,
        "extraction_confidence": 1.0,
        "confidence": 1.0,
        "scratchpad__": {
          "citation": [
            {
              "page": 2,
              "matching_text": "| Total requested amount in CHF | 30000 |",
              "bounding_boxes": [
                {
                  "x": 45.0,
                  "y": 653.0,
                  "w": 149.0,
                  "h": 11.0
                }
              ],
              "page_dimensions": {
                "width": 595.0,
                "height": 842.0
              }
            }
          ]
        },
        "value__": {
          "citation": [
            {
              "page": 2,
              "matching_text": "| Total requested amount in CHF | 30000 |",
              "bounding_boxes": [
                {
                  "x": 45.0,
                  "y": 653.0,
                  "w": 149.0,
                  "h": 11.0
                }
              ],
              "page_dimensions": {
                "width": 595.0,
                "height": 842.0
              }
            },
            {
              "page": 20,
              "matching_text": "| A – Total Direct Costs (i + ii) |                                     |                                                  | 30000        |",
              "bounding_boxes": [
                {
                  "x": 71.0,
                  "y": 140.0,
                  "w": 466.0,
                  "h": 418.0
                }
              ],
              "page_dimensions": {
                "width": 595.25,
                "height": 842.0
              }
            }
          ]
        },
        "parsing_confidence__": {
          "citation": [
            {
              "page": 8,
              "matching_text": "In addition, I took part in the implementation of a tip-sample distance control system for MFM [3], where the distance between probe and sample can be measured and controlled within 1 nm.",
              "bounding_boxes": [
                {
                  "x": 77.0,
                  "y": 154.0,
                  "w": 458.0,
                  "h": 122.0
                }
              ],
              "page_dimensions": {
                "width": 595.29998779,
                "height": 841.90002441
              }
            },
            {
              "page": 22,
              "matching_text": "1",
              "bounding_boxes": [
                {
                  "x": 567.0,
                  "y": 798.0,
                  "w": 3.0,
                  "h": 6.0
                }
              ],
              "page_dimensions": {
                "width": 595.25,
                "height": 842.0
              }
            }
          ]
        },
        "extraction_confidence__": {
          "citation": [
            {
              "page": 8,
              "matching_text": "In addition, I took part in the implementation of a tip-sample distance control system for MFM [3], where the distance between probe and sample can be measured and controlled within 1 nm.",
              "bounding_boxes": [
                {
                  "x": 77.0,
                  "y": 154.0,
                  "w": 458.0,
                  "h": 122.0
                }
              ],
              "page_dimensions": {
                "width": 595.29998779,
                "height": 841.90002441
              }
            },
            {
              "page": 22,
              "matching_text": "1",
              "bounding_boxes": [
                {
                  "x": 567.0,
                  "y": 798.0,
                  "w": 3.0,
                  "h": 6.0
                }
              ],
              "page_dimensions": {
                "width": 595.25,
                "height": 842.0
              }
            }
          ]
        },
        "confidence__": {
          "citation": [
            {
              "page": 8,
              "matching_text": "In addition, I took part in the implementation of a tip-sample distance control system for MFM [3], where the distance between probe and sample can be measured and controlled within 1 nm.",
              "bounding_boxes": [
                {
                  "x": 77.0,
                  "y": 154.0,
                  "w": 458.0,
                  "h": 122.0
                }
              ],
              "page_dimensions": {
                "width": 595.29998779,
                "height": 841.90002441
              }
            },
            {
              "page": 22,
              "matching_text": "1",
              "bounding_boxes": [
                {
                  "x": 567.0,
                  "y": 798.0,
                  "w": 3.0,
                  "h": 6.0
                }
              ],
              "page_dimensions": {
                "width": 595.25,
                "height": 842.0
              }
            }
          ]
        }
      },
      "work_packages": [
        {
          "wp_identifier": {
            "parsing_confidence": 1.0,
            "extraction_confidence": 1.0,
            "confidence": 1.0
          },
          "wp_title": {
            "parsing_confidence": 1.0,
            "extraction_confidence": 0.9998920654032908,
            "confidence": 0.9998920654032908
          },
          "reasoning": "VERBATIM EXTRACTION"
        },
        {
          "wp_identifier": {
            "parsing_confidence": 1.0,
            "extraction_confidence": 1.0,
            "confidence": 1.0
          },
          "wp_title": {
            "parsing_confidence": 1.0,
            "extraction_confidence": 1.0,
            "confidence": 1.0
          },
          "reasoning": "VERBATIM EXTRACTION"
        },
        {
          "wp_identifier": {
            "parsing_confidence": 1.0,
            "extraction_confidence": 1.0,
            "confidence": 1.0
          },
          "wp_title": {
            "parsing_confidence": 1.0,
            "extraction_confidence": 0.999999970213439,
            "confidence": 0.999999970213439
          },
          "reasoning": "VERBATIM EXTRACTION"
        },
        {
          "wp_identifier": {
            "parsing_confidence": 1.0,
            "extraction_confidence": 1.0,
            "confidence": 1.0
          },
          "wp_title": {
            "parsing_confidence": 1.0,
            "extraction_confidence": 0.9999987379600276,
            "confidence": 0.9999987379600276
          },
          "reasoning": "VERBATIM EXTRACTION"
        }
      ]
    },
    "usage": {
      "num_pages_extracted": 22,
      "num_document_tokens": 11886,
      "num_output_tokens": 6855
    },
    "parse_job_id": "33582b78-0a61-4fc4-8ea0-223332c310ad"
  },
  "config": {
    "chunk_mode": "PAGE",
    "citation_bbox": true,
    "cite_sources": true,
    "confidence_scores": true,
    "extract_model": "openai-gpt-4-1",
    "extraction_mode": "PREMIUM",
    "extraction_target": "PER_DOC",
    "high_resolution_mode": true,
    "invalidate_cache": false,
    "multimodal_fast_mode": false,
    "num_pages_context": null,
    "page_range": null,
    "parse_model": "gemini-2.5-pro",
    "priority": null,
    "system_prompt": "\n  EXTRACTION STRATEGY:\n  1. PRIMARY: Look for data in the specified location/table/section\n  2. FALLBACK: If not found, search broader document context for semantically equivalent information\n  3. FLEXIBILITY: Allow for format variations, OCR errors, and synonym usage\n\n  LOCATION FLEXIBILITY:\n  - Handle table format variations (column/row order, spacing, naming)\n  - Consider synonyms and equivalent terms\n  - Account for OCR/parsing errors that may affect document quality\n\n  QUALITY STANDARDS:\n  - Extract actual values found in the document\n  - If uncertain, provide best interpretation with appropriate confidence\n  - Only return null if the information category truly doesn't exist\n  - Convert abbreviated amounts (k=1000) to full numbers where applicable\n  \n\n  METADATA EXTRACTION FOCUS:\n  - Project identification: title, acronym, duration, start date\n  - Applicant details: names, institutions, functions, addresses\n  - Project categorization: Explore/Establish/Contribute classification\n  - Keywords and abstract information from research proposal sections\n  ",
    "use_reasoning": true
  },
  "job_id": "200b8359-599b-4794-9e24-7b6c04344943",
  "extraction_agent_id": "1426fae4-e92a-4aca-b51a-1f002e4ce7da",
  "created_at": "2026-01-21T18:27:06.800123+00:00",
  "updated_at": "2026-01-21T18:29:09.604827+00:00"
}