{
  "document_path": "raw/ORD_files/Explore/Gugerli/application/WSL_GUGERLI.pdf",
  "status": "success",
  "data": {
    "project_category": "Explore Projects",
    "main_applicant_institution": "WSL",
    "main_applicant_function": "Project leader DNL",
    "main_applicant_first_name": "Felix",
    "main_applicant_surname": "Gugerli",
    "main_applicant_laboratory_name": "Biodiversity and Conservation Biology",
    "main_applicant_postcode": 8903,
    "main_applicant_city": "Birmensdorf",
    "all_applicants": [
      {
        "eth_domain_institution": "WSL",
        "function_title": "Dr.",
        "first_name": "Felix",
        "surname": "Gugerli",
        "postcode": 8903
      },
      {
        "eth_domain_institution": "Eawag",
        "function_title": "Dr.",
        "first_name": "Philine",
        "surname": "Feulner",
        "postcode": 6047
      },
      {
        "eth_domain_institution": "Eawag",
        "function_title": "Dr.",
        "first_name": "Alexandra Anh-Thu",
        "surname": "Weber",
        "postcode": 8600
      },
      {
        "eth_domain_institution": "ETH Zürich",
        "function_title": "Dr.",
        "first_name": "Martin C.",
        "surname": "Fischer",
        "postcode": 8092
      },
      {
        "eth_domain_institution": "WSL",
        "function_title": "Dr.",
        "first_name": "Corine",
        "surname": "Buser",
        "postcode": 8903
      },
      {
        "eth_domain_institution": "WSL",
        "function_title": "Dr.",
        "first_name": "Ionut",
        "surname": "Iosifescu Enescu",
        "postcode": 8903
      },
      {
        "eth_domain_institution": "WSL",
        "function_title": "Informatician",
        "first_name": "Lukas",
        "surname": "Wotruba",
        "postcode": 8903
      }
    ],
    "project_title": "Promoting Open Research Data practice for genetic diversity (meta)datasets (GenDiB-ORD)",
    "project_acronym": "GenDiB-ORD",
    "project_abstract": "The prototype of a new national database on intra-specific genetic diversity in populations of wild species in Switzerland, GenDiB, is currently being developed as part of a project co-financed by the Federal Office for the Environment (FOEN). With this ORD initiative proposal, we aim at (i) development of new tools to support simple procedures for dataset up-/download and to implement attractive visualization features and (ii) community building among researchers and stakeholders through various interactive communication means. Our dedicated activities, in parallel to further developing GenDiB as a beta version for subsequent permanent operation and maintenance, should promote the standardized use of GenDiB as the core repository for respective datasets within the community of researchers and stakeholders in conservation management in Switzerland, and possibly beyond. Integrating GenDiB into the national network of database holding species-level occurrence data (InfoSpecies) will complement these databases to cover the genetic level of biodiversity, which is fundamental for population and species persistence in the context of environmental change.",
    "keywords": [
      "ORD community building",
      "intra-specific genetic diversity",
      "data upload and download",
      "data visualization",
      "communication"
    ],
    "start_date": "1 Oct 2024",
    "project_duration_months": 9,
    "total_budget_requested": 75000.0,
    "work_packages": [
      {
        "wp_identifier": "WP1",
        "wp_title": "Tool development"
      },
      {
        "wp_identifier": "WP2",
        "wp_title": "Community building"
      }
    ]
  },
  "metadata": {
    "schema_name": "ORDMetadata",
    "extraction_mode": "PREMIUM",
    "attempts": 1
  },
  "extraction_metadata": {
    "field_metadata": {
      "project_category": {
        "reasoning": "VERBATIM EXTRACTION",
        "parsing_confidence": 1.0,
        "extraction_confidence": 1.0,
        "confidence": 1.0,
        "value__": {
          "citation": [
            {
              "page": 1,
              "matching_text": "# ETH-Domain ORD Program - Measure 1 \"Explore Projects\" Call 2 - Deadline 29th February 2024 (17:00 CET)",
              "bounding_boxes": [
                {
                  "x": 32.0,
                  "y": 140.0,
                  "w": 516.0,
                  "h": 77.0
                }
              ],
              "page_dimensions": {
                "width": 595.0,
                "height": 842.0
              }
            },
            {
              "page": 55,
              "matching_text": "**Explanation:** For the 2nd Explore projects call with deadline on the 29th February 2024, the WSL Management Board received four internal applications.",
              "bounding_boxes": [
                {
                  "x": 96.0,
                  "y": 477.0,
                  "w": 405.0,
                  "h": 52.0
                }
              ],
              "page_dimensions": {
                "width": 595.32,
                "height": 841.92
              }
            },
            {
              "page": 56,
              "matching_text": "To\nETH-Domain ORD Program\nExplore Track",
              "bounding_boxes": [
                {
                  "x": 110.0,
                  "y": 147.0,
                  "w": 130.0,
                  "h": 32.0
                }
              ],
              "page_dimensions": {
                "width": 594.96,
                "height": 841.92
              }
            }
          ]
        },
        "parsing_confidence__": {
          "citation": [
            {
              "page": 7,
              "matching_text": "Page 1/4",
              "bounding_boxes": [
                {
                  "x": 52.0,
                  "y": 819.0,
                  "w": 30.0,
                  "h": 8.0
                }
              ],
              "page_dimensions": {
                "width": 595.29998779,
                "height": 841.90002441
              }
            },
            {
              "page": 54,
              "matching_text": "ETH Zurich\nProf. Dr. Alex Widmer\nCHN G21.1\nUniversitätstrasse 16\n8092 Zurich, Switzerland",
              "bounding_boxes": [
                {
                  "x": 339.0,
                  "y": 88.0,
                  "w": 95.0,
                  "h": 52.0
                }
              ],
              "page_dimensions": {
                "width": 595.0,
                "height": 842.0
              }
            },
            {
              "page": 56,
              "matching_text": "1/2 Eawag: Swiss Federal Institute of Aquatic Science and Technology",
              "bounding_boxes": [
                {
                  "x": 357.0,
                  "y": 805.0,
                  "w": 207.0,
                  "h": 7.0
                }
              ],
              "page_dimensions": {
                "width": 594.96,
                "height": 841.92
              }
            }
          ]
        },
        "extraction_confidence__": {
          "citation": [
            {
              "page": 7,
              "matching_text": "Page 1/4",
              "bounding_boxes": [
                {
                  "x": 52.0,
                  "y": 819.0,
                  "w": 30.0,
                  "h": 8.0
                }
              ],
              "page_dimensions": {
                "width": 595.29998779,
                "height": 841.90002441
              }
            },
            {
              "page": 54,
              "matching_text": "ETH Zurich\nProf. Dr. Alex Widmer\nCHN G21.1\nUniversitätstrasse 16\n8092 Zurich, Switzerland",
              "bounding_boxes": [
                {
                  "x": 339.0,
                  "y": 88.0,
                  "w": 95.0,
                  "h": 52.0
                }
              ],
              "page_dimensions": {
                "width": 595.0,
                "height": 842.0
              }
            },
            {
              "page": 56,
              "matching_text": "1/2 Eawag: Swiss Federal Institute of Aquatic Science and Technology",
              "bounding_boxes": [
                {
                  "x": 357.0,
                  "y": 805.0,
                  "w": 207.0,
                  "h": 7.0
                }
              ],
              "page_dimensions": {
                "width": 594.96,
                "height": 841.92
              }
            }
          ]
        },
        "confidence__": {
          "citation": [
            {
              "page": 7,
              "matching_text": "Page 1/4",
              "bounding_boxes": [
                {
                  "x": 52.0,
                  "y": 819.0,
                  "w": 30.0,
                  "h": 8.0
                }
              ],
              "page_dimensions": {
                "width": 595.29998779,
                "height": 841.90002441
              }
            },
            {
              "page": 54,
              "matching_text": "ETH Zurich\nProf. Dr. Alex Widmer\nCHN G21.1\nUniversitätstrasse 16\n8092 Zurich, Switzerland",
              "bounding_boxes": [
                {
                  "x": 339.0,
                  "y": 88.0,
                  "w": 95.0,
                  "h": 52.0
                }
              ],
              "page_dimensions": {
                "width": 595.0,
                "height": 842.0
              }
            },
            {
              "page": 56,
              "matching_text": "1/2 Eawag: Swiss Federal Institute of Aquatic Science and Technology",
              "bounding_boxes": [
                {
                  "x": 357.0,
                  "y": 805.0,
                  "w": 207.0,
                  "h": 7.0
                }
              ],
              "page_dimensions": {
                "width": 594.96,
                "height": 841.92
              }
            }
          ]
        }
      },
      "main_applicant_institution": {
        "reasoning": "VERBATIM EXTRACTION",
        "parsing_confidence": 1.0,
        "extraction_confidence": 1.0,
        "confidence": 1.0,
        "value__": {
          "citation": [
            {
              "page": 1,
              "matching_text": "ETH Zürich EPFL PAUL SCHERRER INSTITUT PSI WSL Empa Materials Science and Technology eawag aquatic research",
              "bounding_boxes": [
                {
                  "x": 277.15,
                  "y": 107.73,
                  "w": 256.09,
                  "h": 285.39
                }
              ],
              "page_dimensions": {
                "width": 595.0,
                "height": 842.0
              }
            },
            {
              "page": 33,
              "matching_text": "ETH BOARD\nETH zürich EPFL PAUL SCHERRER INSTITUT PSI WSL Empa Materials Science and Technology eawag aquatic research",
              "bounding_boxes": [
                {
                  "x": 556.0,
                  "y": 825.0,
                  "w": 6.0,
                  "h": 15.0
                }
              ],
              "page_dimensions": {
                "width": 595.2,
                "height": 841.92
              }
            },
            {
              "page": 55,
              "matching_text": "Swiss Federal Research Institute WSL",
              "bounding_boxes": [
                {
                  "x": 82.0,
                  "y": 612.0,
                  "w": 188.0,
                  "h": 29.0
                }
              ],
              "page_dimensions": {
                "width": 595.32,
                "height": 841.92
              }
            },
            {
              "page": 56,
              "matching_text": "...ology at Eawag, support the application of **Felix Gugerli Künzle** for an *ORD Explore* project at WSL for the project entitled Promoting Open Research Data practice for genetic diversity (meta)datas...",
              "bounding_boxes": [
                {
                  "x": 110.0,
                  "y": 385.0,
                  "w": 455.0,
                  "h": 80.0
                }
              ],
              "page_dimensions": {
                "width": 594.96,
                "height": 841.92
              }
            }
          ]
        },
        "parsing_confidence__": {
          "citation": [
            {
              "page": 7,
              "matching_text": "Page 1/4",
              "bounding_boxes": [
                {
                  "x": 52.0,
                  "y": 819.0,
                  "w": 30.0,
                  "h": 8.0
                }
              ],
              "page_dimensions": {
                "width": 595.29998779,
                "height": 841.90002441
              }
            },
            {
              "page": 29,
              "matching_text": "Page 1/3",
              "bounding_boxes": [
                {
                  "x": 52.0,
                  "y": 819.0,
                  "w": 30.0,
                  "h": 8.0
                }
              ],
              "page_dimensions": {
                "width": 595.29998779,
                "height": 841.90002441
              }
            },
            {
              "page": 54,
              "matching_text": "ETH Zurich\nProf. Dr. Alex Widmer\nCHN G21.1\nUniversitätstrasse 16\n8092 Zurich, Switzerland",
              "bounding_boxes": [
                {
                  "x": 339.0,
                  "y": 88.0,
                  "w": 95.0,
                  "h": 52.0
                }
              ],
              "page_dimensions": {
                "width": 595.0,
                "height": 842.0
              }
            },
            {
              "page": 56,
              "matching_text": "1/2 Eawag: Swiss Federal Institute of Aquatic Science and Technology",
              "bounding_boxes": [
                {
                  "x": 357.0,
                  "y": 805.0,
                  "w": 207.0,
                  "h": 7.0
                }
              ],
              "page_dimensions": {
                "width": 594.96,
                "height": 841.92
              }
            }
          ]
        },
        "extraction_confidence__": {
          "citation": [
            {
              "page": 7,
              "matching_text": "Page 1/4",
              "bounding_boxes": [
                {
                  "x": 52.0,
                  "y": 819.0,
                  "w": 30.0,
                  "h": 8.0
                }
              ],
              "page_dimensions": {
                "width": 595.29998779,
                "height": 841.90002441
              }
            },
            {
              "page": 29,
              "matching_text": "Page 1/3",
              "bounding_boxes": [
                {
                  "x": 52.0,
                  "y": 819.0,
                  "w": 30.0,
                  "h": 8.0
                }
              ],
              "page_dimensions": {
                "width": 595.29998779,
                "height": 841.90002441
              }
            },
            {
              "page": 54,
              "matching_text": "ETH Zurich\nProf. Dr. Alex Widmer\nCHN G21.1\nUniversitätstrasse 16\n8092 Zurich, Switzerland",
              "bounding_boxes": [
                {
                  "x": 339.0,
                  "y": 88.0,
                  "w": 95.0,
                  "h": 52.0
                }
              ],
              "page_dimensions": {
                "width": 595.0,
                "height": 842.0
              }
            },
            {
              "page": 56,
              "matching_text": "1/2 Eawag: Swiss Federal Institute of Aquatic Science and Technology",
              "bounding_boxes": [
                {
                  "x": 357.0,
                  "y": 805.0,
                  "w": 207.0,
                  "h": 7.0
                }
              ],
              "page_dimensions": {
                "width": 594.96,
                "height": 841.92
              }
            }
          ]
        },
        "confidence__": {
          "citation": [
            {
              "page": 7,
              "matching_text": "Page 1/4",
              "bounding_boxes": [
                {
                  "x": 52.0,
                  "y": 819.0,
                  "w": 30.0,
                  "h": 8.0
                }
              ],
              "page_dimensions": {
                "width": 595.29998779,
                "height": 841.90002441
              }
            },
            {
              "page": 29,
              "matching_text": "Page 1/3",
              "bounding_boxes": [
                {
                  "x": 52.0,
                  "y": 819.0,
                  "w": 30.0,
                  "h": 8.0
                }
              ],
              "page_dimensions": {
                "width": 595.29998779,
                "height": 841.90002441
              }
            },
            {
              "page": 54,
              "matching_text": "ETH Zurich\nProf. Dr. Alex Widmer\nCHN G21.1\nUniversitätstrasse 16\n8092 Zurich, Switzerland",
              "bounding_boxes": [
                {
                  "x": 339.0,
                  "y": 88.0,
                  "w": 95.0,
                  "h": 52.0
                }
              ],
              "page_dimensions": {
                "width": 595.0,
                "height": 842.0
              }
            },
            {
              "page": 56,
              "matching_text": "1/2 Eawag: Swiss Federal Institute of Aquatic Science and Technology",
              "bounding_boxes": [
                {
                  "x": 357.0,
                  "y": 805.0,
                  "w": 207.0,
                  "h": 7.0
                }
              ],
              "page_dimensions": {
                "width": 594.96,
                "height": 841.92
              }
            }
          ]
        },
        "scratchpad__": {
          "citation": [
            {
              "page": 54,
              "matching_text": "Fischer for an *ORD Explore* project at the Swiss Federal Research Institute WSL (PI Dr.",
              "bounding_boxes": [
                {
                  "x": 60.0,
                  "y": 385.0,
                  "w": 472.0,
                  "h": 35.0
                }
              ],
              "page_dimensions": {
                "width": 595.0,
                "height": 842.0
              }
            },
            {
              "page": 56,
              "matching_text": "We, **Philine Feulner** group leader of Fish Genomics in the Department of Fish Ecology & Evolution at Eawag and **Alexandra Anh-Thu Weber** group leader of Adaptation & Conservation Genomics in th...",
              "bounding_boxes": [
                {
                  "x": 110.0,
                  "y": 385.0,
                  "w": 455.0,
                  "h": 80.0
                }
              ],
              "page_dimensions": {
                "width": 594.96,
                "height": 841.92
              }
            }
          ]
        }
      },
      "main_applicant_function": {
        "reasoning": "While 'Dr.' appears as a function/title in one table, this is an honorific and not the applicant's function in context. 'Project leader DNL' is explicitly listed as the current position of the main applicant and is the relevant professional function required by the extraction schema.",
        "parsing_confidence": 1.0,
        "extraction_confidence": 0.9999999515968389,
        "confidence": 0.9999999515968389,
        "value__": {
          "citation": [
            {
              "page": 2,
              "matching_text": "| Function (Title)                   | Dr.               |",
              "bounding_boxes": [
                {
                  "x": 44.0,
                  "y": 377.0,
                  "w": 185.0,
                  "h": 74.0
                }
              ],
              "page_dimensions": {
                "width": 595.0,
                "height": 842.0
              }
            },
            {
              "page": 29,
              "matching_text": "Lukas Wotruba\nCurrent position(s): Project leader DNL",
              "bounding_boxes": [
                {
                  "x": 78.0,
                  "y": 211.0,
                  "w": 190.0,
                  "h": 24.0
                }
              ],
              "page_dimensions": {
                "width": 595.29998779,
                "height": 841.90002441
              }
            }
          ]
        },
        "parsing_confidence__": {
          "citation": [
            {
              "page": 7,
              "matching_text": "Page 1/4",
              "bounding_boxes": [
                {
                  "x": 52.0,
                  "y": 819.0,
                  "w": 30.0,
                  "h": 8.0
                }
              ],
              "page_dimensions": {
                "width": 595.29998779,
                "height": 841.90002441
              }
            },
            {
              "page": 29,
              "matching_text": "Achievement 1",
              "bounding_boxes": [
                {
                  "x": 79.0,
                  "y": 761.0,
                  "w": 71.0,
                  "h": 9.0
                }
              ],
              "page_dimensions": {
                "width": 595.29998779,
                "height": 841.90002441
              }
            }
          ]
        },
        "extraction_confidence__": {
          "citation": [
            {
              "page": 7,
              "matching_text": "Page 1/4",
              "bounding_boxes": [
                {
                  "x": 52.0,
                  "y": 819.0,
                  "w": 30.0,
                  "h": 8.0
                }
              ],
              "page_dimensions": {
                "width": 595.29998779,
                "height": 841.90002441
              }
            }
          ]
        },
        "confidence__": {
          "citation": [
            {
              "page": 7,
              "matching_text": "Page 1/4",
              "bounding_boxes": [
                {
                  "x": 52.0,
                  "y": 819.0,
                  "w": 30.0,
                  "h": 8.0
                }
              ],
              "page_dimensions": {
                "width": 595.29998779,
                "height": 841.90002441
              }
            }
          ]
        },
        "scratchpad__": {
          "citation": [
            {
              "page": 29,
              "matching_text": "Lukas Wotruba\nCurrent position(s): Project leader DNL",
              "bounding_boxes": [
                {
                  "x": 78.0,
                  "y": 211.0,
                  "w": 190.0,
                  "h": 24.0
                }
              ],
              "page_dimensions": {
                "width": 595.29998779,
                "height": 841.90002441
              }
            }
          ]
        }
      },
      "main_applicant_first_name": {
        "reasoning": "Multiple independent references (application table, several support letters) confirm 'Felix' as the main applicant's first name. Only a single CV for 'Lukas' as 'Project leader DNL' appears, but not tagged as main applicant, and all other evidence points to Felix. VERBATIM EXTRACTION.",
        "parsing_confidence": 1.0,
        "extraction_confidence": 1.0,
        "confidence": 1.0,
        "value__": {
          "citation": [
            {
              "page": 1,
              "matching_text": "Felix Gugerli | Applicant ID - ORD2000136",
              "bounding_boxes": [
                {
                  "x": 323.0,
                  "y": 40.0,
                  "w": 235.0,
                  "h": 12.0
                }
              ],
              "page_dimensions": {
                "width": 595.0,
                "height": 842.0
              }
            },
            {
              "page": 29,
              "matching_text": "Lukas Wotruba\nCurrent position(s): Project leader DNL",
              "bounding_boxes": [
                {
                  "x": 78.0,
                  "y": 211.0,
                  "w": 190.0,
                  "h": 24.0
                }
              ],
              "page_dimensions": {
                "width": 595.29998779,
                "height": 841.90002441
              }
            },
            {
              "page": 55,
              "matching_text": "Felix Gugerli for an ORD Explore project in the WSL Research Unit \"Biodiversity and Conservation Biology\" for the project entitled **“Promoting Open Research Data practice for genetic diversity (meta)...",
              "bounding_boxes": [
                {
                  "x": 80.0,
                  "y": 209.0,
                  "w": 418.0,
                  "h": 51.0
                }
              ],
              "page_dimensions": {
                "width": 595.32,
                "height": 841.92
              }
            },
            {
              "page": 56,
              "matching_text": "...& Conservation Genomics in the Department of Aquatic Ecology at Eawag, support the application of **Felix Gugerli Künzle** for an *ORD Explore* project at WSL for the project entitled Promoting Open R...",
              "bounding_boxes": [
                {
                  "x": 110.0,
                  "y": 385.0,
                  "w": 455.0,
                  "h": 80.0
                }
              ],
              "page_dimensions": {
                "width": 594.96,
                "height": 841.92
              }
            }
          ]
        },
        "parsing_confidence__": {
          "citation": [
            {
              "page": 7,
              "matching_text": "Page 1/4",
              "bounding_boxes": [
                {
                  "x": 52.0,
                  "y": 819.0,
                  "w": 30.0,
                  "h": 8.0
                }
              ],
              "page_dimensions": {
                "width": 595.29998779,
                "height": 841.90002441
              }
            },
            {
              "page": 29,
              "matching_text": "Page 1/3",
              "bounding_boxes": [
                {
                  "x": 52.0,
                  "y": 819.0,
                  "w": 30.0,
                  "h": 8.0
                }
              ],
              "page_dimensions": {
                "width": 595.29998779,
                "height": 841.90002441
              }
            },
            {
              "page": 54,
              "matching_text": "ETH Zurich\nProf. Dr. Alex Widmer\nCHN G21.1\nUniversitätstrasse 16\n8092 Zurich, Switzerland",
              "bounding_boxes": [
                {
                  "x": 339.0,
                  "y": 88.0,
                  "w": 95.0,
                  "h": 52.0
                }
              ],
              "page_dimensions": {
                "width": 595.0,
                "height": 842.0
              }
            },
            {
              "page": 56,
              "matching_text": "1/2 Eawag: Swiss Federal Institute of Aquatic Science and Technology",
              "bounding_boxes": [
                {
                  "x": 357.0,
                  "y": 805.0,
                  "w": 207.0,
                  "h": 7.0
                }
              ],
              "page_dimensions": {
                "width": 594.96,
                "height": 841.92
              }
            }
          ]
        },
        "extraction_confidence__": {
          "citation": [
            {
              "page": 7,
              "matching_text": "Page 1/4",
              "bounding_boxes": [
                {
                  "x": 52.0,
                  "y": 819.0,
                  "w": 30.0,
                  "h": 8.0
                }
              ],
              "page_dimensions": {
                "width": 595.29998779,
                "height": 841.90002441
              }
            },
            {
              "page": 29,
              "matching_text": "Page 1/3",
              "bounding_boxes": [
                {
                  "x": 52.0,
                  "y": 819.0,
                  "w": 30.0,
                  "h": 8.0
                }
              ],
              "page_dimensions": {
                "width": 595.29998779,
                "height": 841.90002441
              }
            },
            {
              "page": 54,
              "matching_text": "ETH Zurich\nProf. Dr. Alex Widmer\nCHN G21.1\nUniversitätstrasse 16\n8092 Zurich, Switzerland",
              "bounding_boxes": [
                {
                  "x": 339.0,
                  "y": 88.0,
                  "w": 95.0,
                  "h": 52.0
                }
              ],
              "page_dimensions": {
                "width": 595.0,
                "height": 842.0
              }
            },
            {
              "page": 56,
              "matching_text": "1/2 Eawag: Swiss Federal Institute of Aquatic Science and Technology",
              "bounding_boxes": [
                {
                  "x": 357.0,
                  "y": 805.0,
                  "w": 207.0,
                  "h": 7.0
                }
              ],
              "page_dimensions": {
                "width": 594.96,
                "height": 841.92
              }
            }
          ]
        },
        "confidence__": {
          "citation": [
            {
              "page": 7,
              "matching_text": "Page 1/4",
              "bounding_boxes": [
                {
                  "x": 52.0,
                  "y": 819.0,
                  "w": 30.0,
                  "h": 8.0
                }
              ],
              "page_dimensions": {
                "width": 595.29998779,
                "height": 841.90002441
              }
            },
            {
              "page": 29,
              "matching_text": "Page 1/3",
              "bounding_boxes": [
                {
                  "x": 52.0,
                  "y": 819.0,
                  "w": 30.0,
                  "h": 8.0
                }
              ],
              "page_dimensions": {
                "width": 595.29998779,
                "height": 841.90002441
              }
            },
            {
              "page": 54,
              "matching_text": "ETH Zurich\nProf. Dr. Alex Widmer\nCHN G21.1\nUniversitätstrasse 16\n8092 Zurich, Switzerland",
              "bounding_boxes": [
                {
                  "x": 339.0,
                  "y": 88.0,
                  "w": 95.0,
                  "h": 52.0
                }
              ],
              "page_dimensions": {
                "width": 595.0,
                "height": 842.0
              }
            },
            {
              "page": 56,
              "matching_text": "1/2 Eawag: Swiss Federal Institute of Aquatic Science and Technology",
              "bounding_boxes": [
                {
                  "x": 357.0,
                  "y": 805.0,
                  "w": 207.0,
                  "h": 7.0
                }
              ],
              "page_dimensions": {
                "width": 594.96,
                "height": 841.92
              }
            }
          ]
        },
        "scratchpad__": {
          "citation": [
            {
              "page": 56,
              "matching_text": "This letter thereby confirms that **Felix Gugerli Künzle** is fully entitled to execute the above-mentioned project in the Laboratory of Fish Genomics and Adaptation & Conservation Genomics, headed...",
              "bounding_boxes": [
                {
                  "x": 109.0,
                  "y": 483.0,
                  "w": 455.0,
                  "h": 80.0
                }
              ],
              "page_dimensions": {
                "width": 594.96,
                "height": 841.92
              }
            }
          ]
        }
      },
      "main_applicant_surname": {
        "reasoning": "Although 'Gugerli Künzle' appears in the support letter, throughout the main application forms and central applicant table, the surname entered is 'Gugerli'. The other surname 'Wotruba' appears in a CV for another team member and is not supported as the main applicant in other critical document sections. Therefore, 'Gugerli' is the appropriate main applicant surname for extraction.",
        "parsing_confidence": 1.0,
        "extraction_confidence": 1.0,
        "confidence": 1.0,
        "value__": {
          "citation": [
            {
              "page": 1,
              "matching_text": "Felix Gugerli | Applicant ID - ORD2000136",
              "bounding_boxes": [
                {
                  "x": 323.0,
                  "y": 40.0,
                  "w": 235.0,
                  "h": 12.0
                }
              ],
              "page_dimensions": {
                "width": 595.0,
                "height": 842.0
              }
            },
            {
              "page": 29,
              "matching_text": "Lukas Wotruba\nCurrent position(s): Project leader DNL",
              "bounding_boxes": [
                {
                  "x": 78.0,
                  "y": 211.0,
                  "w": 190.0,
                  "h": 24.0
                }
              ],
              "page_dimensions": {
                "width": 595.29998779,
                "height": 841.90002441
              }
            },
            {
              "page": 48,
              "matching_text": "Pärli R, Lieberherr E, Holderegger R, Gugerli F, Widmer A, Fischer MC 2021. Developing a monitoring program of genetic diversity: What do the stakeholders say? Conservation Genetics 22: 673–684.",
              "bounding_boxes": [
                {
                  "x": 72.0,
                  "y": 317.0,
                  "w": 465.0,
                  "h": 52.0
                }
              ],
              "page_dimensions": {
                "width": 595.2,
                "height": 841.92
              }
            },
            {
              "page": 57,
              "matching_text": "We have actively discussed the proposal with Dr Gugerli Künzle and agreed to collaborate on the project.",
              "bounding_boxes": [
                {
                  "x": 110.0,
                  "y": 191.0,
                  "w": 455.0,
                  "h": 66.0
                }
              ],
              "page_dimensions": {
                "width": 594.96,
                "height": 841.92
              }
            }
          ]
        },
        "parsing_confidence__": {
          "citation": [
            {
              "page": 8,
              "matching_text": "(1) Ecological genomics",
              "bounding_boxes": [
                {
                  "x": 78.0,
                  "y": 572.0,
                  "w": 457.0,
                  "h": 108.0
                }
              ],
              "page_dimensions": {
                "width": 595.29998779,
                "height": 841.90002441
              }
            },
            {
              "page": 29,
              "matching_text": "Achievement 1",
              "bounding_boxes": [
                {
                  "x": 79.0,
                  "y": 761.0,
                  "w": 71.0,
                  "h": 9.0
                }
              ],
              "page_dimensions": {
                "width": 595.29998779,
                "height": 841.90002441
              }
            },
            {
              "page": 54,
              "matching_text": "ETH Zurich\nProf. Dr. Alex Widmer\nCHN G21.1\nUniversitätstrasse 16\n8092 Zurich, Switzerland",
              "bounding_boxes": [
                {
                  "x": 339.0,
                  "y": 88.0,
                  "w": 95.0,
                  "h": 52.0
                }
              ],
              "page_dimensions": {
                "width": 595.0,
                "height": 842.0
              }
            },
            {
              "page": 56,
              "matching_text": "1/2 Eawag: Swiss Federal Institute of Aquatic Science and Technology",
              "bounding_boxes": [
                {
                  "x": 357.0,
                  "y": 805.0,
                  "w": 207.0,
                  "h": 7.0
                }
              ],
              "page_dimensions": {
                "width": 594.96,
                "height": 841.92
              }
            }
          ]
        },
        "extraction_confidence__": {
          "citation": [
            {
              "page": 8,
              "matching_text": "(1) Ecological genomics",
              "bounding_boxes": [
                {
                  "x": 78.0,
                  "y": 572.0,
                  "w": 457.0,
                  "h": 108.0
                }
              ],
              "page_dimensions": {
                "width": 595.29998779,
                "height": 841.90002441
              }
            },
            {
              "page": 29,
              "matching_text": "Achievement 1",
              "bounding_boxes": [
                {
                  "x": 79.0,
                  "y": 761.0,
                  "w": 71.0,
                  "h": 9.0
                }
              ],
              "page_dimensions": {
                "width": 595.29998779,
                "height": 841.90002441
              }
            },
            {
              "page": 54,
              "matching_text": "ETH Zurich\nProf. Dr. Alex Widmer\nCHN G21.1\nUniversitätstrasse 16\n8092 Zurich, Switzerland",
              "bounding_boxes": [
                {
                  "x": 339.0,
                  "y": 88.0,
                  "w": 95.0,
                  "h": 52.0
                }
              ],
              "page_dimensions": {
                "width": 595.0,
                "height": 842.0
              }
            },
            {
              "page": 56,
              "matching_text": "1/2 Eawag: Swiss Federal Institute of Aquatic Science and Technology",
              "bounding_boxes": [
                {
                  "x": 357.0,
                  "y": 805.0,
                  "w": 207.0,
                  "h": 7.0
                }
              ],
              "page_dimensions": {
                "width": 594.96,
                "height": 841.92
              }
            }
          ]
        },
        "confidence__": {
          "citation": [
            {
              "page": 8,
              "matching_text": "(1) Ecological genomics",
              "bounding_boxes": [
                {
                  "x": 78.0,
                  "y": 572.0,
                  "w": 457.0,
                  "h": 108.0
                }
              ],
              "page_dimensions": {
                "width": 595.29998779,
                "height": 841.90002441
              }
            },
            {
              "page": 29,
              "matching_text": "Achievement 1",
              "bounding_boxes": [
                {
                  "x": 79.0,
                  "y": 761.0,
                  "w": 71.0,
                  "h": 9.0
                }
              ],
              "page_dimensions": {
                "width": 595.29998779,
                "height": 841.90002441
              }
            },
            {
              "page": 54,
              "matching_text": "ETH Zurich\nProf. Dr. Alex Widmer\nCHN G21.1\nUniversitätstrasse 16\n8092 Zurich, Switzerland",
              "bounding_boxes": [
                {
                  "x": 339.0,
                  "y": 88.0,
                  "w": 95.0,
                  "h": 52.0
                }
              ],
              "page_dimensions": {
                "width": 595.0,
                "height": 842.0
              }
            },
            {
              "page": 56,
              "matching_text": "1/2 Eawag: Swiss Federal Institute of Aquatic Science and Technology",
              "bounding_boxes": [
                {
                  "x": 357.0,
                  "y": 805.0,
                  "w": 207.0,
                  "h": 7.0
                }
              ],
              "page_dimensions": {
                "width": 594.96,
                "height": 841.92
              }
            }
          ]
        },
        "scratchpad__": {
          "citation": [
            {
              "page": 56,
              "matching_text": "This letter thereby confirms that **Felix Gugerli Künzle** is fully entitled to execute the above-mentioned project in the Laboratory of Fish Genomics and Adaptation & Conservation Genomics, headed...",
              "bounding_boxes": [
                {
                  "x": 109.0,
                  "y": 483.0,
                  "w": 455.0,
                  "h": 80.0
                }
              ],
              "page_dimensions": {
                "width": 594.96,
                "height": 841.92
              }
            }
          ]
        }
      },
      "main_applicant_laboratory_name": {
        "reasoning": "VERBATIM EXTRACTION",
        "parsing_confidence": 1.0,
        "extraction_confidence": 1.0,
        "confidence": 1.0,
        "value__": {
          "citation": [
            {
              "page": 3,
              "matching_text": "Biodiversity and Conservation Biology\nZürcherstrasse 111\n8903 Birmensdorf",
              "bounding_boxes": [
                {
                  "x": 44.0,
                  "y": 485.0,
                  "w": 171.0,
                  "h": 36.0
                }
              ],
              "page_dimensions": {
                "width": 595.0,
                "height": 842.0
              }
            }
          ]
        },
        "parsing_confidence__": {
          "citation": [
            {
              "page": 7,
              "matching_text": "Page 1/4",
              "bounding_boxes": [
                {
                  "x": 52.0,
                  "y": 819.0,
                  "w": 30.0,
                  "h": 8.0
                }
              ],
              "page_dimensions": {
                "width": 595.29998779,
                "height": 841.90002441
              }
            }
          ]
        },
        "extraction_confidence__": {
          "citation": [
            {
              "page": 7,
              "matching_text": "Page 1/4",
              "bounding_boxes": [
                {
                  "x": 52.0,
                  "y": 819.0,
                  "w": 30.0,
                  "h": 8.0
                }
              ],
              "page_dimensions": {
                "width": 595.29998779,
                "height": 841.90002441
              }
            }
          ]
        },
        "confidence__": {
          "citation": [
            {
              "page": 7,
              "matching_text": "Page 1/4",
              "bounding_boxes": [
                {
                  "x": 52.0,
                  "y": 819.0,
                  "w": 30.0,
                  "h": 8.0
                }
              ],
              "page_dimensions": {
                "width": 595.29998779,
                "height": 841.90002441
              }
            }
          ]
        }
      },
      "main_applicant_postcode": {
        "reasoning": "VERBATIM EXTRACTION",
        "parsing_confidence": 1.0,
        "extraction_confidence": 1.0,
        "confidence": 1.0,
        "scratchpad__": {
          "citation": [
            {
              "page": 1,
              "matching_text": "| Postcode / Zipcode...",
              "bounding_boxes": [
                {
                  "x": 43.0,
                  "y": 589.0,
                  "w": 500.0,
                  "h": 37.0
                }
              ],
              "page_dimensions": {
                "width": 595.0,
                "height": 842.0
              }
            }
          ]
        },
        "value__": {
          "citation": [
            {
              "page": 4,
              "matching_text": "8903 Birmensdorf",
              "bounding_boxes": [
                {
                  "x": 44.0,
                  "y": 498.0,
                  "w": 162.0,
                  "h": 48.0
                }
              ],
              "page_dimensions": {
                "width": 595.0,
                "height": 842.0
              }
            }
          ]
        },
        "parsing_confidence__": {
          "citation": [
            {
              "page": 7,
              "matching_text": "Page 1/4",
              "bounding_boxes": [
                {
                  "x": 52.0,
                  "y": 819.0,
                  "w": 30.0,
                  "h": 8.0
                }
              ],
              "page_dimensions": {
                "width": 595.29998779,
                "height": 841.90002441
              }
            }
          ]
        },
        "extraction_confidence__": {
          "citation": [
            {
              "page": 7,
              "matching_text": "Page 1/4",
              "bounding_boxes": [
                {
                  "x": 52.0,
                  "y": 819.0,
                  "w": 30.0,
                  "h": 8.0
                }
              ],
              "page_dimensions": {
                "width": 595.29998779,
                "height": 841.90002441
              }
            }
          ]
        },
        "confidence__": {
          "citation": [
            {
              "page": 7,
              "matching_text": "Page 1/4",
              "bounding_boxes": [
                {
                  "x": 52.0,
                  "y": 819.0,
                  "w": 30.0,
                  "h": 8.0
                }
              ],
              "page_dimensions": {
                "width": 595.29998779,
                "height": 841.90002441
              }
            }
          ]
        }
      },
      "main_applicant_city": {
        "reasoning": "VERBATIM EXTRACTION",
        "parsing_confidence": 1.0,
        "extraction_confidence": 1.0,
        "confidence": 1.0,
        "value__": {
          "citation": [
            {
              "page": 4,
              "matching_text": "8903 Birmensdorf",
              "bounding_boxes": [
                {
                  "x": 44.0,
                  "y": 498.0,
                  "w": 162.0,
                  "h": 48.0
                }
              ],
              "page_dimensions": {
                "width": 595.0,
                "height": 842.0
              }
            }
          ]
        },
        "parsing_confidence__": {
          "citation": [
            {
              "page": 7,
              "matching_text": "Page 1/4",
              "bounding_boxes": [
                {
                  "x": 52.0,
                  "y": 819.0,
                  "w": 30.0,
                  "h": 8.0
                }
              ],
              "page_dimensions": {
                "width": 595.29998779,
                "height": 841.90002441
              }
            }
          ]
        },
        "extraction_confidence__": {
          "citation": [
            {
              "page": 7,
              "matching_text": "Page 1/4",
              "bounding_boxes": [
                {
                  "x": 52.0,
                  "y": 819.0,
                  "w": 30.0,
                  "h": 8.0
                }
              ],
              "page_dimensions": {
                "width": 595.29998779,
                "height": 841.90002441
              }
            }
          ]
        },
        "confidence__": {
          "citation": [
            {
              "page": 7,
              "matching_text": "Page 1/4",
              "bounding_boxes": [
                {
                  "x": 52.0,
                  "y": 819.0,
                  "w": 30.0,
                  "h": 8.0
                }
              ],
              "page_dimensions": {
                "width": 595.29998779,
                "height": 841.90002441
              }
            }
          ]
        }
      },
      "all_applicants": [
        {
          "eth_domain_institution": {
            "parsing_confidence": 1.0,
            "extraction_confidence": 1.0,
            "confidence": 1.0
          },
          "function_title": {
            "parsing_confidence": 1.0,
            "extraction_confidence": 1.0,
            "confidence": 1.0
          },
          "first_name": {
            "parsing_confidence": 1.0,
            "extraction_confidence": 1.0,
            "confidence": 1.0
          },
          "surname": {
            "parsing_confidence": 1.0,
            "extraction_confidence": 1.0,
            "confidence": 1.0
          },
          "postcode": {
            "parsing_confidence": 1.0,
            "extraction_confidence": 1.0,
            "confidence": 1.0
          },
          "reasoning": "VERBATIM EXTRACTION"
        },
        {
          "eth_domain_institution": {
            "parsing_confidence": 1.0,
            "extraction_confidence": 0.9999990364997018,
            "confidence": 0.9999990364997018
          },
          "function_title": {
            "parsing_confidence": 1.0,
            "extraction_confidence": 1.0,
            "confidence": 1.0
          },
          "first_name": {
            "parsing_confidence": 1.0,
            "extraction_confidence": 1.0,
            "confidence": 1.0
          },
          "surname": {
            "parsing_confidence": 1.0,
            "extraction_confidence": 0.9999926913986799,
            "confidence": 0.9999926913986799
          },
          "postcode": {
            "parsing_confidence": 1.0,
            "extraction_confidence": 1.0,
            "confidence": 1.0
          },
          "reasoning": "Combined verbatim extraction (main list) and CV context (which assigned a different postcode and function title, but used primary applicant table for consistency as instructed)."
        },
        {
          "eth_domain_institution": {
            "parsing_confidence": 1.0,
            "extraction_confidence": 1.0,
            "confidence": 1.0
          },
          "function_title": {
            "parsing_confidence": 1.0,
            "extraction_confidence": 1.0,
            "confidence": 1.0
          },
          "first_name": {
            "parsing_confidence": 1.0,
            "extraction_confidence": 1.0,
            "confidence": 1.0
          },
          "surname": {
            "parsing_confidence": 1.0,
            "extraction_confidence": 0.9999994859809547,
            "confidence": 0.9999994859809547
          },
          "postcode": {
            "parsing_confidence": 1.0,
            "extraction_confidence": 1.0,
            "confidence": 1.0
          },
          "reasoning": "VERBATIM EXTRACTION (main list). Additional function title 'Group leader' appears in CV, but main applicant list prioritised."
        },
        {
          "eth_domain_institution": {
            "parsing_confidence": 1.0,
            "extraction_confidence": 0.9999861948679375,
            "confidence": 0.9999861948679375
          },
          "function_title": {
            "parsing_confidence": 1.0,
            "extraction_confidence": 1.0,
            "confidence": 1.0
          },
          "first_name": {
            "parsing_confidence": 1.0,
            "extraction_confidence": 1.0,
            "confidence": 1.0
          },
          "surname": {
            "parsing_confidence": 1.0,
            "extraction_confidence": 1.0,
            "confidence": 1.0
          },
          "postcode": {
            "parsing_confidence": 1.0,
            "extraction_confidence": 1.0,
            "confidence": 1.0
          },
          "reasoning": "VERBATIM EXTRACTION from main table, CV confirms institution but function is 'Lecturer / Reader' there; retained 'Dr.' as per main list."
        },
        {
          "eth_domain_institution": {
            "parsing_confidence": 1.0,
            "extraction_confidence": 1.0,
            "confidence": 1.0
          },
          "function_title": {
            "parsing_confidence": 1.0,
            "extraction_confidence": 1.0,
            "confidence": 1.0
          },
          "first_name": {
            "parsing_confidence": 1.0,
            "extraction_confidence": 1.0,
            "confidence": 1.0
          },
          "surname": {
            "parsing_confidence": 1.0,
            "extraction_confidence": 1.0,
            "confidence": 1.0
          },
          "postcode": {
            "parsing_confidence": 1.0,
            "extraction_confidence": 1.0,
            "confidence": 1.0
          },
          "reasoning": "Prioritised main table (surname 'Buser'); CV gives full surname ('Buser-Schöbel') and refined function but lacks postcode."
        },
        {
          "eth_domain_institution": {
            "parsing_confidence": 1.0,
            "extraction_confidence": 1.0,
            "confidence": 1.0
          },
          "function_title": {
            "parsing_confidence": 1.0,
            "extraction_confidence": 1.0,
            "confidence": 1.0
          },
          "first_name": {
            "parsing_confidence": 1.0,
            "extraction_confidence": 1.0,
            "confidence": 1.0
          },
          "surname": {
            "parsing_confidence": 1.0,
            "extraction_confidence": 1.0,
            "confidence": 1.0
          },
          "postcode": {
            "parsing_confidence": 1.0,
            "extraction_confidence": 1.0,
            "confidence": 1.0
          },
          "reasoning": "Maintained info from main applicant table for completeness; CV confirms identity and role details but not postcode."
        },
        {
          "eth_domain_institution": {
            "parsing_confidence": 1.0,
            "extraction_confidence": 1.0,
            "confidence": 1.0
          },
          "function_title": {
            "parsing_confidence": 1.0,
            "extraction_confidence": 1.0,
            "confidence": 1.0
          },
          "first_name": {
            "parsing_confidence": 1.0,
            "extraction_confidence": 1.0,
            "confidence": 1.0
          },
          "surname": {
            "parsing_confidence": 1.0,
            "extraction_confidence": 1.0,
            "confidence": 1.0
          },
          "postcode": {
            "parsing_confidence": 1.0,
            "extraction_confidence": 1.0,
            "confidence": 1.0
          },
          "reasoning": "VERBATIM EXTRACTION"
        }
      ],
      "project_title": {
        "reasoning": "Multiple exact extractions consistently use 'Promoting Open Research Data practice for genetic diversity (meta)datasets (GenDiB-ORD)' as the formal project title, especially in the RESEARCH PROPOSAL table and grant support letters. Small OCR or formatting differences elsewhere ('practice' vs 'Practice', minor punctuation or hyperlink artifacts) do not affect the main, unambiguous project title. The abbreviated/alternate forms ('GenDiB-ORD', etc.) are short-hand references, not the full title.",
        "parsing_confidence": 1.0,
        "extraction_confidence": 0.9999999545996683,
        "confidence": 0.9999999545996683,
        "value__": {
          "citation": [
            {
              "page": 5,
              "matching_text": "...| Promoting Open Research Data Practice for Genetic Diversity (meta)datasets  |",
              "bounding_boxes": [
                {
                  "x": 274.0,
                  "y": 99.0,
                  "w": 235.0,
                  "h": 55.0
                }
              ],
              "page_dimensions": {
                "width": 595.0,
                "height": 842.0
              }
            },
            {
              "page": 34,
              "matching_text": "Promoting Open Research Data practice for genetic diversity [(][(](https://www.infospecies.ch/)https://www.gbif.org/)meta)datasets (GenDiB-ORD)",
              "bounding_boxes": [
                {
                  "x": 70.0,
                  "y": 168.0,
                  "w": 451.0,
                  "h": 13.0
                }
              ],
              "page_dimensions": {
                "width": 595.2,
                "height": 841.92
              }
            },
            {
              "page": 37,
              "matching_text": "In the next step, we want to expand the database and further promote ORD practice to establish GenDiB as a practical tool for standardized open-access storage and sharing of genetic diversity data.",
              "bounding_boxes": [
                {
                  "x": 71.0,
                  "y": 619.0,
                  "w": 466.0,
                  "h": 89.0
                }
              ],
              "page_dimensions": {
                "width": 595.2,
                "height": 841.92
              }
            },
            {
              "page": 44,
              "matching_text": "The GenDiB-ORD project is structured into two work packages (WPs), as outlined in chapter 3 (ORD project plan) and visualized in the Gantt chart below.",
              "bounding_boxes": [
                {
                  "x": 71.0,
                  "y": 299.0,
                  "w": 466.0,
                  "h": 50.0
                }
              ],
              "page_dimensions": {
                "width": 595.2,
                "height": 841.92
              }
            },
            {
              "page": 55,
              "matching_text": "...roject in the WSL Research Unit \"Biodiversity and Conservation Biology\" for the project entitled **“Promoting Open Research Data practice for genetic diversity (meta)datasets (GenDiB-ORD)”**, pending...",
              "bounding_boxes": [
                {
                  "x": 80.0,
                  "y": 209.0,
                  "w": 418.0,
                  "h": 51.0
                }
              ],
              "page_dimensions": {
                "width": 595.32,
                "height": 841.92
              }
            },
            {
              "page": 56,
              "matching_text": "**In support of the grant proposal “Promoting Open Research Data practice for genetic diversity (meta)datasets (GenDiB-ORD)”**",
              "bounding_boxes": [
                {
                  "x": 110.0,
                  "y": 287.0,
                  "w": 450.0,
                  "h": 24.0
                }
              ],
              "page_dimensions": {
                "width": 594.96,
                "height": 841.92
              }
            }
          ]
        },
        "parsing_confidence__": {
          "citation": [
            {
              "page": 8,
              "matching_text": "(1) Ecological genomics",
              "bounding_boxes": [
                {
                  "x": 78.0,
                  "y": 572.0,
                  "w": 457.0,
                  "h": 108.0
                }
              ],
              "page_dimensions": {
                "width": 595.29998779,
                "height": 841.90002441
              }
            },
            {
              "page": 29,
              "matching_text": "Achievement 1",
              "bounding_boxes": [
                {
                  "x": 79.0,
                  "y": 761.0,
                  "w": 71.0,
                  "h": 9.0
                }
              ],
              "page_dimensions": {
                "width": 595.29998779,
                "height": 841.90002441
              }
            },
            {
              "page": 41,
              "matching_text": "1) **Excellence of ORD practice.** Research institutes such as WSL and Eawag have long been and still are determined to provide data holding services to the Swiss research community and beyond.",
              "bounding_boxes": [
                {
                  "x": 71.0,
                  "y": 556.0,
                  "w": 466.0,
                  "h": 148.0
                }
              ],
              "page_dimensions": {
                "width": 595.2,
                "height": 841.92
              }
            },
            {
              "page": 46,
              "matching_text": "Fischer MC, Ruprecht K, Gugerli F, Holderegger R, Widmer A 2021. Pilotstudie für ein Monitoring der genetischen Vielfalt in der Schweiz. N&L Inside 1/21: 11–13.",
              "bounding_boxes": [
                {
                  "x": 72.0,
                  "y": 605.0,
                  "w": 465.0,
                  "h": 32.0
                }
              ],
              "page_dimensions": {
                "width": 595.2,
                "height": 841.92
              }
            },
            {
              "page": 54,
              "matching_text": "ETH Zurich\nProf. Dr. Alex Widmer\nCHN G21.1\nUniversitätstrasse 16\n8092 Zurich, Switzerland",
              "bounding_boxes": [
                {
                  "x": 339.0,
                  "y": 88.0,
                  "w": 95.0,
                  "h": 52.0
                }
              ],
              "page_dimensions": {
                "width": 595.0,
                "height": 842.0
              }
            },
            {
              "page": 56,
              "matching_text": "1/2 Eawag: Swiss Federal Institute of Aquatic Science and Technology",
              "bounding_boxes": [
                {
                  "x": 357.0,
                  "y": 805.0,
                  "w": 207.0,
                  "h": 7.0
                }
              ],
              "page_dimensions": {
                "width": 594.96,
                "height": 841.92
              }
            }
          ]
        },
        "scratchpad__": {
          "citation": [
            {
              "page": 34,
              "matching_text": "Promoting Open Research Data practice for genetic diversity [(][(](https://www.infospecies.ch/)https://www.gbif.org/)meta)datasets (GenDiB-ORD)",
              "bounding_boxes": [
                {
                  "x": 70.0,
                  "y": 168.0,
                  "w": 451.0,
                  "h": 13.0
                }
              ],
              "page_dimensions": {
                "width": 595.2,
                "height": 841.92
              }
            },
            {
              "page": 41,
              "matching_text": "With our project, we will advance ORD practices in the (Swiss) population and conservation genetic research community, given that no repository for geo-referenced data on genetic diversity is at ha...",
              "bounding_boxes": [
                {
                  "x": 71.0,
                  "y": 556.0,
                  "w": 466.0,
                  "h": 148.0
                }
              ],
              "page_dimensions": {
                "width": 595.2,
                "height": 841.92
              }
            },
            {
              "page": 55,
              "matching_text": "Felix Gugerli for an ORD Explore project in the WSL Research Unit \"Biodiversity and Conservation Biology\" for the project entitled **“Promoting Open Research Data practice for genetic diversity (me...",
              "bounding_boxes": [
                {
                  "x": 80.0,
                  "y": 209.0,
                  "w": 418.0,
                  "h": 51.0
                }
              ],
              "page_dimensions": {
                "width": 595.32,
                "height": 841.92
              }
            },
            {
              "page": 56,
              "matching_text": "**In support of the grant proposal “Promoting Open Research Data practice for genetic diversity (meta)datasets (GenDiB-ORD)”**",
              "bounding_boxes": [
                {
                  "x": 110.0,
                  "y": 287.0,
                  "w": 450.0,
                  "h": 24.0
                }
              ],
              "page_dimensions": {
                "width": 594.96,
                "height": 841.92
              }
            }
          ]
        },
        "extraction_confidence__": {
          "citation": [
            {
              "page": 44,
              "matching_text": "| 5.4 PM | software engineer 60%     | 3.0 PM | intern                                | M1-M3 | Milestones   |",
              "bounding_boxes": [
                {
                  "x": 73.0,
                  "y": 356.0,
                  "w": 462.0,
                  "h": 125.0
                }
              ],
              "page_dimensions": {
                "width": 595.2,
                "height": 841.92
              }
            },
            {
              "page": 53,
              "matching_text": "In addition, in-kind efforts by permanent staff at WSL, Eawag, and ETHZ are provided (estimated five person months in total; WSL 3.5 PM, Eawag 1 PM, ETHZ 0.5PM), and other costs will be covered by...",
              "bounding_boxes": [
                {
                  "x": 67.0,
                  "y": 306.0,
                  "w": 697.0,
                  "h": 43.0
                }
              ],
              "page_dimensions": {
                "width": 841.92,
                "height": 595.2
              }
            },
            {
              "page": 56,
              "matching_text": "| Eawag<br/>Seestrasse 79<br/>6047 Kastanienbaum<br/>Switzerland<br/>Phone +41 (0)41 349 21 11<br/>Fax +41 (0)41 349 21 68<br/>[www.eawag.ch](http://www.eawag.ch) | Department of Fish Ecology & Evo...",
              "bounding_boxes": [
                {
                  "x": 0.0,
                  "y": 0.0,
                  "w": 594.96,
                  "h": 841.92
                }
              ],
              "page_dimensions": {
                "width": 594.96,
                "height": 841.92
              }
            }
          ]
        },
        "confidence__": {
          "citation": [
            {
              "page": 44,
              "matching_text": "| 5.4 PM | software engineer 60%     | 3.0 PM | intern                                | M1-M3 | Milestones   |",
              "bounding_boxes": [
                {
                  "x": 73.0,
                  "y": 356.0,
                  "w": 462.0,
                  "h": 125.0
                }
              ],
              "page_dimensions": {
                "width": 595.2,
                "height": 841.92
              }
            },
            {
              "page": 53,
              "matching_text": "In addition, in-kind efforts by permanent staff at WSL, Eawag, and ETHZ are provided (estimated five person months in total; WSL 3.5 PM, Eawag 1 PM, ETHZ 0.5PM), and other costs will be covered by...",
              "bounding_boxes": [
                {
                  "x": 67.0,
                  "y": 306.0,
                  "w": 697.0,
                  "h": 43.0
                }
              ],
              "page_dimensions": {
                "width": 841.92,
                "height": 595.2
              }
            },
            {
              "page": 56,
              "matching_text": "| Eawag<br/>Seestrasse 79<br/>6047 Kastanienbaum<br/>Switzerland<br/>Phone +41 (0)41 349 21 11<br/>Fax +41 (0)41 349 21 68<br/>[www.eawag.ch](http://www.eawag.ch) | Department of Fish Ecology & Evo...",
              "bounding_boxes": [
                {
                  "x": 0.0,
                  "y": 0.0,
                  "w": 594.96,
                  "h": 841.92
                }
              ],
              "page_dimensions": {
                "width": 594.96,
                "height": 841.92
              }
            }
          ]
        }
      },
      "project_acronym": {
        "reasoning": "VERBATIM EXTRACTION",
        "parsing_confidence": 1.0,
        "extraction_confidence": 1.0,
        "confidence": 1.0,
        "value__": {
          "citation": [
            {
              "page": 5,
              "matching_text": "| ----------------------------------------------------- | ------------------------------------- |\n| Letter of support of the Institution for co-financing | 100550::GenDiB-ORD-SupportLetters.pdf |",
              "bounding_boxes": [
                {
                  "x": 276.0,
                  "y": 730.0,
                  "w": 184.0,
                  "h": 26.0
                }
              ],
              "page_dimensions": {
                "width": 595.0,
                "height": 842.0
              }
            }
          ]
        },
        "parsing_confidence__": {
          "citation": [
            {
              "page": 7,
              "matching_text": "Page 1/4",
              "bounding_boxes": [
                {
                  "x": 52.0,
                  "y": 819.0,
                  "w": 30.0,
                  "h": 8.0
                }
              ],
              "page_dimensions": {
                "width": 595.29998779,
                "height": 841.90002441
              }
            }
          ]
        },
        "extraction_confidence__": {
          "citation": [
            {
              "page": 7,
              "matching_text": "Page 1/4",
              "bounding_boxes": [
                {
                  "x": 52.0,
                  "y": 819.0,
                  "w": 30.0,
                  "h": 8.0
                }
              ],
              "page_dimensions": {
                "width": 595.29998779,
                "height": 841.90002441
              }
            }
          ]
        },
        "confidence__": {
          "citation": [
            {
              "page": 7,
              "matching_text": "Page 1/4",
              "bounding_boxes": [
                {
                  "x": 52.0,
                  "y": 819.0,
                  "w": 30.0,
                  "h": 8.0
                }
              ],
              "page_dimensions": {
                "width": 595.29998779,
                "height": 841.90002441
              }
            }
          ]
        }
      },
      "project_abstract": {
        "reasoning": "VERBATIM EXTRACTION",
        "parsing_confidence": 1.0,
        "extraction_confidence": 0.9999990437574843,
        "confidence": 0.9999990437574843,
        "value__": {
          "citation": [
            {
              "page": 5,
              "matching_text": "Our dedicated activities, in parallel to further developing GenDiB as a beta version for subsequent permanent operation and maintenance, should promote the standardized use of GenDiB as the core re...",
              "bounding_boxes": [
                {
                  "x": 43.0,
                  "y": 201.0,
                  "w": 503.0,
                  "h": 134.0
                }
              ],
              "page_dimensions": {
                "width": 595.0,
                "height": 842.0
              }
            }
          ]
        },
        "parsing_confidence__": {
          "citation": [
            {
              "page": 8,
              "matching_text": "(1) Ecological genomics",
              "bounding_boxes": [
                {
                  "x": 78.0,
                  "y": 572.0,
                  "w": 457.0,
                  "h": 108.0
                }
              ],
              "page_dimensions": {
                "width": 595.29998779,
                "height": 841.90002441
              }
            }
          ]
        }
      },
      "keywords": [
        {
          "reasoning": "VERBATIM EXTRACTION",
          "parsing_confidence": 1.0,
          "extraction_confidence": 1.0,
          "confidence": 1.0,
          "value__": {
            "citation": [
              {
                "page": 5,
                "matching_text": "| **Please enter up to 5 keywords that characterise your proposal (separated by commas)**<br/><br/>ORD community building, intra-specific genetic diversity, data upload and download, data visualizatio...",
                "bounding_boxes": [
                  {
                    "x": 44.0,
                    "y": 355.0,
                    "w": 410.0,
                    "h": 11.0
                  }
                ],
                "page_dimensions": {
                  "width": 595.0,
                  "height": 842.0
                }
              }
            ]
          },
          "parsing_confidence__": {
            "citation": [
              {
                "page": 7,
                "matching_text": "Page 1/4",
                "bounding_boxes": [
                  {
                    "x": 52.0,
                    "y": 819.0,
                    "w": 30.0,
                    "h": 8.0
                  }
                ],
                "page_dimensions": {
                  "width": 595.29998779,
                  "height": 841.90002441
                }
              }
            ]
          },
          "extraction_confidence__": {
            "citation": [
              {
                "page": 7,
                "matching_text": "Page 1/4",
                "bounding_boxes": [
                  {
                    "x": 52.0,
                    "y": 819.0,
                    "w": 30.0,
                    "h": 8.0
                  }
                ],
                "page_dimensions": {
                  "width": 595.29998779,
                  "height": 841.90002441
                }
              }
            ]
          },
          "confidence__": {
            "citation": [
              {
                "page": 7,
                "matching_text": "Page 1/4",
                "bounding_boxes": [
                  {
                    "x": 52.0,
                    "y": 819.0,
                    "w": 30.0,
                    "h": 8.0
                  }
                ],
                "page_dimensions": {
                  "width": 595.29998779,
                  "height": 841.90002441
                }
              }
            ]
          }
        },
        {
          "reasoning": "VERBATIM EXTRACTION",
          "parsing_confidence": 1.0,
          "extraction_confidence": 1.0,
          "confidence": 1.0,
          "scratchpad__": {
            "citation": [
              {
                "page": 5,
                "matching_text": "| **Please enter up to 5 keywords that characterise your proposal (separated by commas)**<br/><br/>ORD community building, intra-specific genetic diversity, data upload and download, data visualiza...",
                "bounding_boxes": [
                  {
                    "x": 44.0,
                    "y": 355.0,
                    "w": 410.0,
                    "h": 11.0
                  }
                ],
                "page_dimensions": {
                  "width": 595.0,
                  "height": 842.0
                }
              }
            ]
          },
          "value__": {
            "citation": [
              {
                "page": 5,
                "matching_text": "...5 keywords that characterise your proposal (separated by commas)**<br/><br/>ORD community building, intra-specific genetic diversity, data upload and download, data visualization, communication...",
                "bounding_boxes": [
                  {
                    "x": 44.0,
                    "y": 355.0,
                    "w": 410.0,
                    "h": 11.0
                  }
                ],
                "page_dimensions": {
                  "width": 595.0,
                  "height": 842.0
                }
              }
            ]
          },
          "parsing_confidence__": {
            "citation": [
              {
                "page": 7,
                "matching_text": "Page 1/4",
                "bounding_boxes": [
                  {
                    "x": 52.0,
                    "y": 819.0,
                    "w": 30.0,
                    "h": 8.0
                  }
                ],
                "page_dimensions": {
                  "width": 595.29998779,
                  "height": 841.90002441
                }
              }
            ]
          },
          "extraction_confidence__": {
            "citation": [
              {
                "page": 7,
                "matching_text": "Page 1/4",
                "bounding_boxes": [
                  {
                    "x": 52.0,
                    "y": 819.0,
                    "w": 30.0,
                    "h": 8.0
                  }
                ],
                "page_dimensions": {
                  "width": 595.29998779,
                  "height": 841.90002441
                }
              }
            ]
          },
          "confidence__": {
            "citation": [
              {
                "page": 7,
                "matching_text": "Page 1/4",
                "bounding_boxes": [
                  {
                    "x": 52.0,
                    "y": 819.0,
                    "w": 30.0,
                    "h": 8.0
                  }
                ],
                "page_dimensions": {
                  "width": 595.29998779,
                  "height": 841.90002441
                }
              }
            ]
          }
        },
        {
          "reasoning": "VERBATIM EXTRACTION",
          "parsing_confidence": 1.0,
          "extraction_confidence": 1.0,
          "confidence": 1.0,
          "scratchpad__": {
            "citation": [
              {
                "page": 5,
                "matching_text": "| **Please enter up to 5 keywords that characterise your proposal (separated by commas)**<br/><br/>ORD community building, intra-specific genetic diversity, data upload and download, data visualiza...",
                "bounding_boxes": [
                  {
                    "x": 44.0,
                    "y": 355.0,
                    "w": 410.0,
                    "h": 11.0
                  }
                ],
                "page_dimensions": {
                  "width": 595.0,
                  "height": 842.0
                }
              }
            ]
          },
          "value__": {
            "citation": [
              {
                "page": 5,
                "matching_text": "...proposal (separated by commas)**<br/><br/>ORD community building, intra-specific genetic diversity, data upload and download, data visualization, communication...",
                "bounding_boxes": [
                  {
                    "x": 44.0,
                    "y": 355.0,
                    "w": 410.0,
                    "h": 11.0
                  }
                ],
                "page_dimensions": {
                  "width": 595.0,
                  "height": 842.0
                }
              }
            ]
          },
          "parsing_confidence__": {
            "citation": [
              {
                "page": 7,
                "matching_text": "Page 1/4",
                "bounding_boxes": [
                  {
                    "x": 52.0,
                    "y": 819.0,
                    "w": 30.0,
                    "h": 8.0
                  }
                ],
                "page_dimensions": {
                  "width": 595.29998779,
                  "height": 841.90002441
                }
              }
            ]
          },
          "extraction_confidence__": {
            "citation": [
              {
                "page": 7,
                "matching_text": "Page 1/4",
                "bounding_boxes": [
                  {
                    "x": 52.0,
                    "y": 819.0,
                    "w": 30.0,
                    "h": 8.0
                  }
                ],
                "page_dimensions": {
                  "width": 595.29998779,
                  "height": 841.90002441
                }
              }
            ]
          },
          "confidence__": {
            "citation": [
              {
                "page": 7,
                "matching_text": "Page 1/4",
                "bounding_boxes": [
                  {
                    "x": 52.0,
                    "y": 819.0,
                    "w": 30.0,
                    "h": 8.0
                  }
                ],
                "page_dimensions": {
                  "width": 595.29998779,
                  "height": 841.90002441
                }
              }
            ]
          }
        },
        {
          "reasoning": "VERBATIM EXTRACTION",
          "parsing_confidence": 1.0,
          "extraction_confidence": 1.0,
          "confidence": 1.0,
          "value__": {
            "citation": [
              {
                "page": 5,
                "matching_text": "...mas)**<br/><br/>ORD community building, intra-specific genetic diversity, data upload and download, data visualization, communication...",
                "bounding_boxes": [
                  {
                    "x": 44.0,
                    "y": 355.0,
                    "w": 410.0,
                    "h": 11.0
                  }
                ],
                "page_dimensions": {
                  "width": 595.0,
                  "height": 842.0
                }
              }
            ]
          },
          "parsing_confidence__": {
            "citation": [
              {
                "page": 6,
                "matching_text": "| 1 - Human participants?<br/>Comment                                                                                  | No |",
                "bounding_boxes": [
                  {
                    "x": 38.0,
                    "y": 116.0,
                    "w": 518.0,
                    "h": 377.0
                  }
                ],
                "page_dimensions": {
                  "width": 595.0,
                  "height": 842.0
                }
              }
            ]
          },
          "extraction_confidence__": {
            "citation": [
              {
                "page": 6,
                "matching_text": "| 1 - Human participants?<br/>Comment                                                                                  | No |",
                "bounding_boxes": [
                  {
                    "x": 38.0,
                    "y": 116.0,
                    "w": 518.0,
                    "h": 377.0
                  }
                ],
                "page_dimensions": {
                  "width": 595.0,
                  "height": 842.0
                }
              }
            ]
          },
          "confidence__": {
            "citation": [
              {
                "page": 6,
                "matching_text": "| 1 - Human participants?<br/>Comment                                                                                  | No |",
                "bounding_boxes": [
                  {
                    "x": 38.0,
                    "y": 116.0,
                    "w": 518.0,
                    "h": 377.0
                  }
                ],
                "page_dimensions": {
                  "width": 595.0,
                  "height": 842.0
                }
              }
            ]
          }
        },
        {
          "reasoning": "VERBATIM EXTRACTION",
          "parsing_confidence": 1.0,
          "extraction_confidence": 1.0,
          "confidence": 1.0,
          "value__": {
            "citation": [
              {
                "page": 5,
                "matching_text": "...community building, intra-specific genetic diversity, data upload and download, data visualization, communication...",
                "bounding_boxes": [
                  {
                    "x": 44.0,
                    "y": 355.0,
                    "w": 410.0,
                    "h": 11.0
                  }
                ],
                "page_dimensions": {
                  "width": 595.0,
                  "height": 842.0
                }
              }
            ]
          },
          "parsing_confidence__": {
            "citation": [
              {
                "page": 7,
                "matching_text": "Page 1/4",
                "bounding_boxes": [
                  {
                    "x": 52.0,
                    "y": 819.0,
                    "w": 30.0,
                    "h": 8.0
                  }
                ],
                "page_dimensions": {
                  "width": 595.29998779,
                  "height": 841.90002441
                }
              }
            ]
          },
          "extraction_confidence__": {
            "citation": [
              {
                "page": 7,
                "matching_text": "Page 1/4",
                "bounding_boxes": [
                  {
                    "x": 52.0,
                    "y": 819.0,
                    "w": 30.0,
                    "h": 8.0
                  }
                ],
                "page_dimensions": {
                  "width": 595.29998779,
                  "height": 841.90002441
                }
              }
            ]
          },
          "confidence__": {
            "citation": [
              {
                "page": 7,
                "matching_text": "Page 1/4",
                "bounding_boxes": [
                  {
                    "x": 52.0,
                    "y": 819.0,
                    "w": 30.0,
                    "h": 8.0
                  }
                ],
                "page_dimensions": {
                  "width": 595.29998779,
                  "height": 841.90002441
                }
              }
            ]
          }
        }
      ],
      "start_date": {
        "reasoning": "VERBATIM EXTRACTION",
        "parsing_confidence": 1.0,
        "extraction_confidence": 0.9999996990294446,
        "confidence": 0.9999996990294446,
        "scratchpad__": {
          "citation": [
            {
              "page": 5,
              "matching_text": "| Proposed Starting Date...",
              "bounding_boxes": [
                {
                  "x": 43.0,
                  "y": 377.0,
                  "w": 460.0,
                  "h": 22.0
                }
              ],
              "page_dimensions": {
                "width": 595.0,
                "height": 842.0
              }
            }
          ]
        },
        "value__": {
          "citation": [
            {
              "page": 5,
              "matching_text": "| Proposed Starting Date...",
              "bounding_boxes": [
                {
                  "x": 43.0,
                  "y": 377.0,
                  "w": 460.0,
                  "h": 22.0
                }
              ],
              "page_dimensions": {
                "width": 595.0,
                "height": 842.0
              }
            }
          ]
        },
        "parsing_confidence__": {
          "citation": [
            {
              "page": 8,
              "matching_text": "(1) Ecological genomics",
              "bounding_boxes": [
                {
                  "x": 78.0,
                  "y": 572.0,
                  "w": 457.0,
                  "h": 108.0
                }
              ],
              "page_dimensions": {
                "width": 595.29998779,
                "height": 841.90002441
              }
            }
          ]
        }
      },
      "project_duration_months": {
        "reasoning": "VERBATIM EXTRACTION",
        "parsing_confidence": 1.0,
        "extraction_confidence": 1.0,
        "confidence": 1.0,
        "scratchpad__": {
          "citation": [
            {
              "page": 5,
              "matching_text": "| Project duration...",
              "bounding_boxes": [
                {
                  "x": 43.0,
                  "y": 377.0,
                  "w": 460.0,
                  "h": 22.0
                }
              ],
              "page_dimensions": {
                "width": 595.0,
                "height": 842.0
              }
            }
          ]
        },
        "value__": {
          "citation": [
            {
              "page": 7,
              "matching_text": "of Gothenberg) | Universität Zürich - ZH, CH<br/>Institute for Systematic Botany | 08.1993 - 04.1997<br/>3 year(s) 9 month(s) |\n| Master: Diploma in Systematic Botany (supervised by J.J.",
              "bounding_boxes": [
                {
                  "x": 79.0,
                  "y": 365.0,
                  "w": 452.0,
                  "h": 155.0
                }
              ],
              "page_dimensions": {
                "width": 595.29998779,
                "height": 841.90002441
              }
            }
          ]
        },
        "parsing_confidence__": {
          "citation": [
            {
              "page": 7,
              "matching_text": "Page 1/4",
              "bounding_boxes": [
                {
                  "x": 52.0,
                  "y": 819.0,
                  "w": 30.0,
                  "h": 8.0
                }
              ],
              "page_dimensions": {
                "width": 595.29998779,
                "height": 841.90002441
              }
            }
          ]
        },
        "extraction_confidence__": {
          "citation": [
            {
              "page": 7,
              "matching_text": "Page 1/4",
              "bounding_boxes": [
                {
                  "x": 52.0,
                  "y": 819.0,
                  "w": 30.0,
                  "h": 8.0
                }
              ],
              "page_dimensions": {
                "width": 595.29998779,
                "height": 841.90002441
              }
            }
          ]
        },
        "confidence__": {
          "citation": [
            {
              "page": 7,
              "matching_text": "Page 1/4",
              "bounding_boxes": [
                {
                  "x": 52.0,
                  "y": 819.0,
                  "w": 30.0,
                  "h": 8.0
                }
              ],
              "page_dimensions": {
                "width": 595.29998779,
                "height": 841.90002441
              }
            }
          ]
        }
      },
      "total_budget_requested": {
        "reasoning": "The most relevant value for 'total budget requested' is CHF 75,000, as clarified in the budget justification (page 53): 'we ask for CHF 75,000 from the ETH Domain.' The 150,000 CHF on page 5 refers to the total project budget rather than the amount actually requested as a grant. The extraction is based on the explicit amount being \"asked for\" from the funding body, thus fitting the schema requirements.",
        "parsing_confidence": 1.0,
        "extraction_confidence": 1.0,
        "confidence": 1.0,
        "scratchpad__": {
          "citation": [
            {
              "page": 5,
              "matching_text": "| Total requested amount in CHF                         | 150000                                |",
              "bounding_boxes": [
                {
                  "x": 44.0,
                  "y": 730.0,
                  "w": 196.0,
                  "h": 39.0
                }
              ],
              "page_dimensions": {
                "width": 595.0,
                "height": 842.0
              }
            },
            {
              "page": 53,
              "matching_text": "**Budget justification** — The total budget of our proposed project is CHF 150'000, of which we ask for CHF 75'000 from the ETH Domain to complement institutional in-cash contributions.",
              "bounding_boxes": [
                {
                  "x": 67.0,
                  "y": 203.0,
                  "w": 702.0,
                  "h": 101.0
                }
              ],
              "page_dimensions": {
                "width": 841.92,
                "height": 595.2
              }
            }
          ]
        },
        "value__": {
          "citation": [
            {
              "page": 5,
              "matching_text": "| Total requested amount in CHF                         | 150000                                |",
              "bounding_boxes": [
                {
                  "x": 44.0,
                  "y": 730.0,
                  "w": 196.0,
                  "h": 39.0
                }
              ],
              "page_dimensions": {
                "width": 595.0,
                "height": 842.0
              }
            },
            {
              "page": 53,
              "matching_text": "In addition, in-kind efforts by permanent staff at WSL, Eawag, and ETHZ are provided (estimated five person months in total; WSL 3.5 PM, Eawag 1 PM, ETHZ 0.5PM), and other costs will be covered by...",
              "bounding_boxes": [
                {
                  "x": 67.0,
                  "y": 306.0,
                  "w": 697.0,
                  "h": 43.0
                }
              ],
              "page_dimensions": {
                "width": 841.92,
                "height": 595.2
              }
            }
          ]
        },
        "parsing_confidence__": {
          "citation": [
            {
              "page": 7,
              "matching_text": "Page 1/4",
              "bounding_boxes": [
                {
                  "x": 52.0,
                  "y": 819.0,
                  "w": 30.0,
                  "h": 8.0
                }
              ],
              "page_dimensions": {
                "width": 595.29998779,
                "height": 841.90002441
              }
            },
            {
              "page": 54,
              "matching_text": "ETH Zurich\nProf. Dr. Alex Widmer\nCHN G21.1\nUniversitätstrasse 16\n8092 Zurich, Switzerland",
              "bounding_boxes": [
                {
                  "x": 339.0,
                  "y": 88.0,
                  "w": 95.0,
                  "h": 52.0
                }
              ],
              "page_dimensions": {
                "width": 595.0,
                "height": 842.0
              }
            }
          ]
        },
        "extraction_confidence__": {
          "citation": [
            {
              "page": 7,
              "matching_text": "Page 1/4",
              "bounding_boxes": [
                {
                  "x": 52.0,
                  "y": 819.0,
                  "w": 30.0,
                  "h": 8.0
                }
              ],
              "page_dimensions": {
                "width": 595.29998779,
                "height": 841.90002441
              }
            },
            {
              "page": 54,
              "matching_text": "ETH Zurich\nProf. Dr. Alex Widmer\nCHN G21.1\nUniversitätstrasse 16\n8092 Zurich, Switzerland",
              "bounding_boxes": [
                {
                  "x": 339.0,
                  "y": 88.0,
                  "w": 95.0,
                  "h": 52.0
                }
              ],
              "page_dimensions": {
                "width": 595.0,
                "height": 842.0
              }
            }
          ]
        },
        "confidence__": {
          "citation": [
            {
              "page": 7,
              "matching_text": "Page 1/4",
              "bounding_boxes": [
                {
                  "x": 52.0,
                  "y": 819.0,
                  "w": 30.0,
                  "h": 8.0
                }
              ],
              "page_dimensions": {
                "width": 595.29998779,
                "height": 841.90002441
              }
            },
            {
              "page": 54,
              "matching_text": "ETH Zurich\nProf. Dr. Alex Widmer\nCHN G21.1\nUniversitätstrasse 16\n8092 Zurich, Switzerland",
              "bounding_boxes": [
                {
                  "x": 339.0,
                  "y": 88.0,
                  "w": 95.0,
                  "h": 52.0
                }
              ],
              "page_dimensions": {
                "width": 595.0,
                "height": 842.0
              }
            }
          ]
        }
      },
      "work_packages": [
        {
          "wp_identifier": {
            "parsing_confidence": 1.0,
            "extraction_confidence": 1.0,
            "confidence": 1.0
          },
          "wp_title": {
            "parsing_confidence": 1.0,
            "extraction_confidence": 0.9999988303613937,
            "confidence": 0.9999988303613937
          },
          "reasoning": "VERBATIM EXTRACTION"
        },
        {
          "wp_identifier": {
            "parsing_confidence": 1.0,
            "extraction_confidence": 1.0,
            "confidence": 1.0
          },
          "wp_title": {
            "parsing_confidence": 1.0,
            "extraction_confidence": 1.0,
            "confidence": 1.0
          },
          "reasoning": "VERBATIM EXTRACTION"
        }
      ]
    },
    "usage": {
      "num_pages_extracted": 58,
      "num_document_tokens": 37766,
      "num_output_tokens": 10523
    },
    "parse_job_id": "6c12059b-a9e3-48d4-b62e-ffc45361b539"
  },
  "config": {
    "chunk_mode": "PAGE",
    "citation_bbox": true,
    "cite_sources": true,
    "confidence_scores": true,
    "extract_model": "openai-gpt-4-1",
    "extraction_mode": "PREMIUM",
    "extraction_target": "PER_DOC",
    "high_resolution_mode": true,
    "invalidate_cache": false,
    "multimodal_fast_mode": false,
    "num_pages_context": null,
    "page_range": null,
    "parse_model": "gemini-2.5-pro",
    "priority": null,
    "system_prompt": "\n  EXTRACTION STRATEGY:\n  1. PRIMARY: Look for data in the specified location/table/section\n  2. FALLBACK: If not found, search broader document context for semantically equivalent information\n  3. FLEXIBILITY: Allow for format variations, OCR errors, and synonym usage\n\n  LOCATION FLEXIBILITY:\n  - Handle table format variations (column/row order, spacing, naming)\n  - Consider synonyms and equivalent terms\n  - Account for OCR/parsing errors that may affect document quality\n\n  QUALITY STANDARDS:\n  - Extract actual values found in the document\n  - If uncertain, provide best interpretation with appropriate confidence\n  - Only return null if the information category truly doesn't exist\n  - Convert abbreviated amounts (k=1000) to full numbers where applicable\n  \n\n  METADATA EXTRACTION FOCUS:\n  - Project identification: title, acronym, duration, start date\n  - Applicant details: names, institutions, functions, addresses\n  - Project categorization: Explore/Establish/Contribute classification\n  - Keywords and abstract information from research proposal sections\n  ",
    "use_reasoning": true
  },
  "job_id": "edbdb5c6-8ac3-45df-9c58-7e5ab7f63e92",
  "extraction_agent_id": "1426fae4-e92a-4aca-b51a-1f002e4ce7da",
  "created_at": "2026-01-21T17:08:11.306887+00:00",
  "updated_at": "2026-01-21T17:11:53.705090+00:00"
}